// class version 50.0 (50)
// access flags 0x21
public class net/minecraft/client/renderer/ItemRenderer {

  // compiled from: ItemRenderer.java

  @Lnet/minecraftforge/fml/relauncher/SideOnly;(value=Lnet/minecraftforge/fml/relauncher/Side;.CLIENT)
  // access flags 0x1008
  static synthetic INNERCLASS net/minecraft/client/renderer/ItemRenderer$1 null null
  // access flags 0x4019
  public final static enum INNERCLASS net/minecraft/client/renderer/block/model/ItemCameraTransforms$TransformType net/minecraft/client/renderer/block/model/ItemCameraTransforms TransformType
  // access flags 0x4019
  public final static enum INNERCLASS net/minecraftforge/client/event/RenderBlockOverlayEvent$OverlayType net/minecraftforge/client/event/RenderBlockOverlayEvent OverlayType
  // access flags 0x4019
  public final static enum INNERCLASS net/minecraft/client/renderer/GlStateManager$SourceFactor net/minecraft/client/renderer/GlStateManager SourceFactor
  // access flags 0x4019
  public final static enum INNERCLASS net/minecraft/client/renderer/GlStateManager$DestFactor net/minecraft/client/renderer/GlStateManager DestFactor

  // access flags 0x1A
  private final static Lnet/minecraft/util/ResourceLocation; RES_MAP_BACKGROUND

  // access flags 0x1A
  private final static Lnet/minecraft/util/ResourceLocation; RES_UNDERWATER_OVERLAY

  // access flags 0x12
  private final Lnet/minecraft/client/Minecraft; mc

  // access flags 0x2
  private Lnet/minecraft/item/ItemStack; itemStackMainHand

  // access flags 0x2
  private Lnet/minecraft/item/ItemStack; itemStackOffHand

  // access flags 0x2
  private F equippedProgressMainHand

  // access flags 0x2
  private F prevEquippedProgressMainHand

  // access flags 0x2
  private F equippedProgressOffHand

  // access flags 0x2
  private F prevEquippedProgressOffHand

  // access flags 0x12
  private final Lnet/minecraft/client/renderer/entity/RenderManager; renderManager

  // access flags 0x12
  private final Lnet/minecraft/client/renderer/RenderItem; itemRenderer

  // access flags 0x1
  public <init>(Lnet/minecraft/client/Minecraft;)V
   L0
    LINENUMBER 51 L0
    ALOAD 0
    INVOKESPECIAL java/lang/Object.<init> ()V
   L1
    LINENUMBER 52 L1
    ALOAD 0
    ALOAD 1
    PUTFIELD net/minecraft/client/renderer/ItemRenderer.mc : Lnet/minecraft/client/Minecraft;
   L2
    LINENUMBER 53 L2
    ALOAD 0
    ALOAD 1
    INVOKEVIRTUAL net/minecraft/client/Minecraft.getRenderManager ()Lnet/minecraft/client/renderer/entity/RenderManager;
    PUTFIELD net/minecraft/client/renderer/ItemRenderer.renderManager : Lnet/minecraft/client/renderer/entity/RenderManager;
   L3
    LINENUMBER 54 L3
    ALOAD 0
    ALOAD 1
    INVOKEVIRTUAL net/minecraft/client/Minecraft.getRenderItem ()Lnet/minecraft/client/renderer/RenderItem;
    PUTFIELD net/minecraft/client/renderer/ItemRenderer.itemRenderer : Lnet/minecraft/client/renderer/RenderItem;
   L4
    LINENUMBER 55 L4
    RETURN
   L5
    LOCALVARIABLE this Lnet/minecraft/client/renderer/ItemRenderer; L0 L5 0
    LOCALVARIABLE mcIn Lnet/minecraft/client/Minecraft; L0 L5 1
    MAXSTACK = 2
    MAXLOCALS = 2

  // access flags 0x1
  public renderItem(Lnet/minecraft/entity/EntityLivingBase;Lnet/minecraft/item/ItemStack;Lnet/minecraft/client/renderer/block/model/ItemCameraTransforms$TransformType;)V
   L0
    LINENUMBER 59 L0
    ALOAD 0
    ALOAD 1
    ALOAD 2
    ALOAD 3
    ICONST_0
    INVOKEVIRTUAL net/minecraft/client/renderer/ItemRenderer.renderItemSide (Lnet/minecraft/entity/EntityLivingBase;Lnet/minecraft/item/ItemStack;Lnet/minecraft/client/renderer/block/model/ItemCameraTransforms$TransformType;Z)V
   L1
    LINENUMBER 60 L1
    RETURN
   L2
    LOCALVARIABLE this Lnet/minecraft/client/renderer/ItemRenderer; L0 L2 0
    LOCALVARIABLE entityIn Lnet/minecraft/entity/EntityLivingBase; L0 L2 1
    LOCALVARIABLE heldStack Lnet/minecraft/item/ItemStack; L0 L2 2
    LOCALVARIABLE transform Lnet/minecraft/client/renderer/block/model/ItemCameraTransforms$TransformType; L0 L2 3
    MAXSTACK = 5
    MAXLOCALS = 4

  // access flags 0x1
  public renderItemSide(Lnet/minecraft/entity/EntityLivingBase;Lnet/minecraft/item/ItemStack;Lnet/minecraft/client/renderer/block/model/ItemCameraTransforms$TransformType;Z)V
   L0
    LINENUMBER 64 L0
    ALOAD 2
    IFNULL L1
   L2
    LINENUMBER 66 L2
    ALOAD 2
    INVOKEVIRTUAL net/minecraft/item/ItemStack.getItem ()Lnet/minecraft/item/Item;
    ASTORE 5
   L3
    LINENUMBER 67 L3
    ALOAD 5
    INVOKESTATIC net/minecraft/block/Block.getBlockFromItem (Lnet/minecraft/item/Item;)Lnet/minecraft/block/Block;
    ASTORE 6
   L4
    LINENUMBER 68 L4
    INVOKESTATIC net/minecraft/client/renderer/GlStateManager.pushMatrix ()V
   L5
    LINENUMBER 69 L5
    ALOAD 0
    GETFIELD net/minecraft/client/renderer/ItemRenderer.itemRenderer : Lnet/minecraft/client/renderer/RenderItem;
    ALOAD 2
    INVOKEVIRTUAL net/minecraft/client/renderer/RenderItem.shouldRenderItemIn3D (Lnet/minecraft/item/ItemStack;)Z
    IFEQ L6
    ALOAD 0
    ALOAD 6
    INVOKESPECIAL net/minecraft/client/renderer/ItemRenderer.isBlockTranslucent (Lnet/minecraft/block/Block;)Z
    IFEQ L6
    ICONST_1
    GOTO L7
   L6
   FRAME FULL [net/minecraft/client/renderer/ItemRenderer net/minecraft/entity/EntityLivingBase net/minecraft/item/ItemStack net/minecraft/client/renderer/block/model/ItemCameraTransforms$TransformType I net/minecraft/item/Item net/minecraft/block/Block] []
    ICONST_0
   L7
   FRAME FULL [net/minecraft/client/renderer/ItemRenderer net/minecraft/entity/EntityLivingBase net/minecraft/item/ItemStack net/minecraft/client/renderer/block/model/ItemCameraTransforms$TransformType I net/minecraft/item/Item net/minecraft/block/Block] [I]
    ISTORE 7
   L8
    LINENUMBER 71 L8
    ILOAD 7
    IFEQ L9
   L10
    LINENUMBER 73 L10
    ICONST_0
    INVOKESTATIC net/minecraft/client/renderer/GlStateManager.depthMask (Z)V
   L9
    LINENUMBER 76 L9
   FRAME FULL [net/minecraft/client/renderer/ItemRenderer net/minecraft/entity/EntityLivingBase net/minecraft/item/ItemStack net/minecraft/client/renderer/block/model/ItemCameraTransforms$TransformType I net/minecraft/item/Item net/minecraft/block/Block I] []
    ALOAD 0
    GETFIELD net/minecraft/client/renderer/ItemRenderer.itemRenderer : Lnet/minecraft/client/renderer/RenderItem;
    ALOAD 2
    ALOAD 1
    ALOAD 3
    ILOAD 4
    INVOKEVIRTUAL net/minecraft/client/renderer/RenderItem.renderItem (Lnet/minecraft/item/ItemStack;Lnet/minecraft/entity/EntityLivingBase;Lnet/minecraft/client/renderer/block/model/ItemCameraTransforms$TransformType;Z)V
   L11
    LINENUMBER 78 L11
    ILOAD 7
    IFEQ L12
   L13
    LINENUMBER 80 L13
    ICONST_1
    INVOKESTATIC net/minecraft/client/renderer/GlStateManager.depthMask (Z)V
   L12
    LINENUMBER 83 L12
   FRAME FULL [net/minecraft/client/renderer/ItemRenderer net/minecraft/entity/EntityLivingBase net/minecraft/item/ItemStack net/minecraft/client/renderer/block/model/ItemCameraTransforms$TransformType I net/minecraft/item/Item net/minecraft/block/Block I] []
    INVOKESTATIC net/minecraft/client/renderer/GlStateManager.popMatrix ()V
   L1
    LINENUMBER 85 L1
   FRAME FULL [net/minecraft/client/renderer/ItemRenderer net/minecraft/entity/EntityLivingBase net/minecraft/item/ItemStack net/minecraft/client/renderer/block/model/ItemCameraTransforms$TransformType I] []
    RETURN
   L14
    LOCALVARIABLE item Lnet/minecraft/item/Item; L3 L1 5
    LOCALVARIABLE block Lnet/minecraft/block/Block; L4 L1 6
    LOCALVARIABLE flag Z L8 L1 7
    LOCALVARIABLE this Lnet/minecraft/client/renderer/ItemRenderer; L0 L14 0
    LOCALVARIABLE entitylivingbaseIn Lnet/minecraft/entity/EntityLivingBase; L0 L14 1
    LOCALVARIABLE heldStack Lnet/minecraft/item/ItemStack; L0 L14 2
    LOCALVARIABLE transform Lnet/minecraft/client/renderer/block/model/ItemCameraTransforms$TransformType; L0 L14 3
    LOCALVARIABLE leftHanded Z L0 L14 4
    MAXSTACK = 5
    MAXLOCALS = 8

  // access flags 0x2
  private isBlockTranslucent(Lnet/minecraft/block/Block;)Z
    @Ljavax/annotation/Nullable;() // parameter 0
   L0
    LINENUMBER 92 L0
    ALOAD 1
    IFNULL L1
    ALOAD 1
    INVOKEVIRTUAL net/minecraft/block/Block.getBlockLayer ()Lnet/minecraft/util/BlockRenderLayer;
    GETSTATIC net/minecraft/util/BlockRenderLayer.TRANSLUCENT : Lnet/minecraft/util/BlockRenderLayer;
    IF_ACMPNE L1
    ICONST_1
    GOTO L2
   L1
   FRAME FULL [net/minecraft/client/renderer/ItemRenderer net/minecraft/block/Block] []
    ICONST_0
   L2
   FRAME FULL [net/minecraft/client/renderer/ItemRenderer net/minecraft/block/Block] [I]
    IRETURN
   L3
    LOCALVARIABLE this Lnet/minecraft/client/renderer/ItemRenderer; L0 L3 0
    LOCALVARIABLE blockIn Lnet/minecraft/block/Block; L0 L3 1
    MAXSTACK = 2
    MAXLOCALS = 2

  // access flags 0x2
  private rotateArroundXAndY(FF)V
   L0
    LINENUMBER 100 L0
    INVOKESTATIC net/minecraft/client/renderer/GlStateManager.pushMatrix ()V
   L1
    LINENUMBER 101 L1
    FLOAD 1
    FCONST_1
    FCONST_0
    FCONST_0
    INVOKESTATIC net/minecraft/client/renderer/GlStateManager.rotate (FFFF)V
   L2
    LINENUMBER 102 L2
    FLOAD 2
    FCONST_0
    FCONST_1
    FCONST_0
    INVOKESTATIC net/minecraft/client/renderer/GlStateManager.rotate (FFFF)V
   L3
    LINENUMBER 103 L3
    INVOKESTATIC net/minecraft/client/renderer/RenderHelper.enableStandardItemLighting ()V
   L4
    LINENUMBER 104 L4
    INVOKESTATIC net/minecraft/client/renderer/GlStateManager.popMatrix ()V
   L5
    LINENUMBER 105 L5
    RETURN
   L6
    LOCALVARIABLE this Lnet/minecraft/client/renderer/ItemRenderer; L0 L6 0
    LOCALVARIABLE angle F L0 L6 1
    LOCALVARIABLE angleY F L0 L6 2
    MAXSTACK = 4
    MAXLOCALS = 3

  // access flags 0x2
  private setLightmap()V
   L0
    LINENUMBER 109 L0
    ALOAD 0
    GETFIELD net/minecraft/client/renderer/ItemRenderer.mc : Lnet/minecraft/client/Minecraft;
    GETFIELD net/minecraft/client/Minecraft.thePlayer : Lnet/minecraft/client/entity/EntityPlayerSP;
    ASTORE 1
   L1
    LINENUMBER 110 L1
    ALOAD 0
    GETFIELD net/minecraft/client/renderer/ItemRenderer.mc : Lnet/minecraft/client/Minecraft;
    GETFIELD net/minecraft/client/Minecraft.theWorld : Lnet/minecraft/client/multiplayer/WorldClient;
    NEW net/minecraft/util/math/BlockPos
    DUP
    ALOAD 1
    GETFIELD net/minecraft/client/entity/AbstractClientPlayer.posX : D
    ALOAD 1
    GETFIELD net/minecraft/client/entity/AbstractClientPlayer.posY : D
    ALOAD 1
    INVOKEVIRTUAL net/minecraft/client/entity/AbstractClientPlayer.getEyeHeight ()F
    F2D
    DADD
    ALOAD 1
    GETFIELD net/minecraft/client/entity/AbstractClientPlayer.posZ : D
    INVOKESPECIAL net/minecraft/util/math/BlockPos.<init> (DDD)V
    ICONST_0
    INVOKEVIRTUAL net/minecraft/client/multiplayer/WorldClient.getCombinedLight (Lnet/minecraft/util/math/BlockPos;I)I
    ISTORE 2
   L2
    LINENUMBER 111 L2
    ILOAD 2
    LDC 65535
    IAND
    I2F
    FSTORE 3
   L3
    LINENUMBER 112 L3
    ILOAD 2
    BIPUSH 16
    ISHR
    I2F
    FSTORE 4
   L4
    LINENUMBER 113 L4
    GETSTATIC net/minecraft/client/renderer/OpenGlHelper.lightmapTexUnit : I
    FLOAD 3
    FLOAD 4
    INVOKESTATIC net/minecraft/client/renderer/OpenGlHelper.setLightmapTextureCoords (IFF)V
   L5
    LINENUMBER 114 L5
    RETURN
   L6
    LOCALVARIABLE this Lnet/minecraft/client/renderer/ItemRenderer; L0 L6 0
    LOCALVARIABLE abstractclientplayer Lnet/minecraft/client/entity/AbstractClientPlayer; L1 L6 1
    LOCALVARIABLE i I L2 L6 2
    LOCALVARIABLE f F L3 L6 3
    LOCALVARIABLE f1 F L4 L6 4
    MAXSTACK = 9
    MAXLOCALS = 5

  // access flags 0x2
  private rotateArm(F)V
   L0
    LINENUMBER 118 L0
    ALOAD 0
    GETFIELD net/minecraft/client/renderer/ItemRenderer.mc : Lnet/minecraft/client/Minecraft;
    GETFIELD net/minecraft/client/Minecraft.thePlayer : Lnet/minecraft/client/entity/EntityPlayerSP;
    ASTORE 2
   L1
    LINENUMBER 119 L1
    ALOAD 2
    GETFIELD net/minecraft/client/entity/EntityPlayerSP.prevRenderArmPitch : F
    ALOAD 2
    GETFIELD net/minecraft/client/entity/EntityPlayerSP.renderArmPitch : F
    ALOAD 2
    GETFIELD net/minecraft/client/entity/EntityPlayerSP.prevRenderArmPitch : F
    FSUB
    FLOAD 1
    FMUL
    FADD
    FSTORE 3
   L2
    LINENUMBER 120 L2
    ALOAD 2
    GETFIELD net/minecraft/client/entity/EntityPlayerSP.prevRenderArmYaw : F
    ALOAD 2
    GETFIELD net/minecraft/client/entity/EntityPlayerSP.renderArmYaw : F
    ALOAD 2
    GETFIELD net/minecraft/client/entity/EntityPlayerSP.prevRenderArmYaw : F
    FSUB
    FLOAD 1
    FMUL
    FADD
    FSTORE 4
   L3
    LINENUMBER 121 L3
    ALOAD 2
    GETFIELD net/minecraft/client/entity/EntityPlayerSP.rotationPitch : F
    FLOAD 3
    FSUB
    LDC 0.1
    FMUL
    FCONST_1
    FCONST_0
    FCONST_0
    INVOKESTATIC net/minecraft/client/renderer/GlStateManager.rotate (FFFF)V
   L4
    LINENUMBER 122 L4
    ALOAD 2
    GETFIELD net/minecraft/client/entity/EntityPlayerSP.rotationYaw : F
    FLOAD 4
    FSUB
    LDC 0.1
    FMUL
    FCONST_0
    FCONST_1
    FCONST_0
    INVOKESTATIC net/minecraft/client/renderer/GlStateManager.rotate (FFFF)V
   L5
    LINENUMBER 123 L5
    RETURN
   L6
    LOCALVARIABLE this Lnet/minecraft/client/renderer/ItemRenderer; L0 L6 0
    LOCALVARIABLE p_187458_1_ F L0 L6 1
    LOCALVARIABLE entityplayersp Lnet/minecraft/client/entity/EntityPlayerSP; L1 L6 2
    LOCALVARIABLE f F L2 L6 3
    LOCALVARIABLE f1 F L3 L6 4
    MAXSTACK = 4
    MAXLOCALS = 5

  // access flags 0x2
  private getMapAngleFromPitch(F)F
   L0
    LINENUMBER 130 L0
    FCONST_1
    FLOAD 1
    LDC 45.0
    FDIV
    FSUB
    LDC 0.1
    FADD
    FSTORE 2
   L1
    LINENUMBER 131 L1
    FLOAD 2
    FCONST_0
    FCONST_1
    INVOKESTATIC net/minecraft/util/math/MathHelper.clamp_float (FFF)F
    FSTORE 2
   L2
    LINENUMBER 132 L2
    FLOAD 2
    LDC 3.1415927
    FMUL
    INVOKESTATIC net/minecraft/util/math/MathHelper.cos (F)F
    FNEG
    LDC 0.5
    FMUL
    LDC 0.5
    FADD
    FSTORE 2
   L3
    LINENUMBER 133 L3
    FLOAD 2
    FRETURN
   L4
    LOCALVARIABLE this Lnet/minecraft/client/renderer/ItemRenderer; L0 L4 0
    LOCALVARIABLE pitch F L0 L4 1
    LOCALVARIABLE f F L1 L4 2
    MAXSTACK = 3
    MAXLOCALS = 3

  // access flags 0x2
  private renderArms()V
   L0
    LINENUMBER 138 L0
    ALOAD 0
    GETFIELD net/minecraft/client/renderer/ItemRenderer.mc : Lnet/minecraft/client/Minecraft;
    GETFIELD net/minecraft/client/Minecraft.thePlayer : Lnet/minecraft/client/entity/EntityPlayerSP;
    INVOKEVIRTUAL net/minecraft/client/entity/EntityPlayerSP.isInvisible ()Z
    IFNE L1
   L2
    LINENUMBER 140 L2
    INVOKESTATIC net/minecraft/client/renderer/GlStateManager.disableCull ()V
   L3
    LINENUMBER 141 L3
    INVOKESTATIC net/minecraft/client/renderer/GlStateManager.pushMatrix ()V
   L4
    LINENUMBER 142 L4
    LDC 90.0
    FCONST_0
    FCONST_1
    FCONST_0
    INVOKESTATIC net/minecraft/client/renderer/GlStateManager.rotate (FFFF)V
   L5
    LINENUMBER 143 L5
    ALOAD 0
    GETSTATIC net/minecraft/util/EnumHandSide.RIGHT : Lnet/minecraft/util/EnumHandSide;
    INVOKESPECIAL net/minecraft/client/renderer/ItemRenderer.renderArm (Lnet/minecraft/util/EnumHandSide;)V
   L6
    LINENUMBER 144 L6
    ALOAD 0
    GETSTATIC net/minecraft/util/EnumHandSide.LEFT : Lnet/minecraft/util/EnumHandSide;
    INVOKESPECIAL net/minecraft/client/renderer/ItemRenderer.renderArm (Lnet/minecraft/util/EnumHandSide;)V
   L7
    LINENUMBER 145 L7
    INVOKESTATIC net/minecraft/client/renderer/GlStateManager.popMatrix ()V
   L8
    LINENUMBER 146 L8
    INVOKESTATIC net/minecraft/client/renderer/GlStateManager.enableCull ()V
   L1
    LINENUMBER 148 L1
   FRAME FULL [net/minecraft/client/renderer/ItemRenderer] []
    RETURN
   L9
    LOCALVARIABLE this Lnet/minecraft/client/renderer/ItemRenderer; L0 L9 0
    MAXSTACK = 4
    MAXLOCALS = 1

  // access flags 0x2
  private renderArm(Lnet/minecraft/util/EnumHandSide;)V
   L0
    LINENUMBER 152 L0
    ALOAD 0
    GETFIELD net/minecraft/client/renderer/ItemRenderer.mc : Lnet/minecraft/client/Minecraft;
    INVOKEVIRTUAL net/minecraft/client/Minecraft.getTextureManager ()Lnet/minecraft/client/renderer/texture/TextureManager;
    ALOAD 0
    GETFIELD net/minecraft/client/renderer/ItemRenderer.mc : Lnet/minecraft/client/Minecraft;
    GETFIELD net/minecraft/client/Minecraft.thePlayer : Lnet/minecraft/client/entity/EntityPlayerSP;
    INVOKEVIRTUAL net/minecraft/client/entity/EntityPlayerSP.getLocationSkin ()Lnet/minecraft/util/ResourceLocation;
    INVOKEVIRTUAL net/minecraft/client/renderer/texture/TextureManager.bindTexture (Lnet/minecraft/util/ResourceLocation;)V
   L1
    LINENUMBER 153 L1
    ALOAD 0
    GETFIELD net/minecraft/client/renderer/ItemRenderer.renderManager : Lnet/minecraft/client/renderer/entity/RenderManager;
    ALOAD 0
    GETFIELD net/minecraft/client/renderer/ItemRenderer.mc : Lnet/minecraft/client/Minecraft;
    GETFIELD net/minecraft/client/Minecraft.thePlayer : Lnet/minecraft/client/entity/EntityPlayerSP;
    INVOKEVIRTUAL net/minecraft/client/renderer/entity/RenderManager.getEntityRenderObject (Lnet/minecraft/entity/Entity;)Lnet/minecraft/client/renderer/entity/Render;
    ASTORE 2
   L2
    LINENUMBER 154 L2
    ALOAD 2
    CHECKCAST net/minecraft/client/renderer/entity/RenderPlayer
    ASTORE 3
   L3
    LINENUMBER 155 L3
    INVOKESTATIC net/minecraft/client/renderer/GlStateManager.pushMatrix ()V
   L4
    LINENUMBER 156 L4
    ALOAD 1
    GETSTATIC net/minecraft/util/EnumHandSide.RIGHT : Lnet/minecraft/util/EnumHandSide;
    IF_ACMPNE L5
    FCONST_1
    GOTO L6
   L5
   FRAME FULL [net/minecraft/client/renderer/ItemRenderer net/minecraft/util/EnumHandSide net/minecraft/client/renderer/entity/Render net/minecraft/client/renderer/entity/RenderPlayer] []
    LDC -1.0
   L6
   FRAME FULL [net/minecraft/client/renderer/ItemRenderer net/minecraft/util/EnumHandSide net/minecraft/client/renderer/entity/Render net/minecraft/client/renderer/entity/RenderPlayer] [F]
    FSTORE 4
   L7
    LINENUMBER 157 L7
    LDC 92.0
    FCONST_0
    FCONST_1
    FCONST_0
    INVOKESTATIC net/minecraft/client/renderer/GlStateManager.rotate (FFFF)V
   L8
    LINENUMBER 158 L8
    LDC 45.0
    FCONST_1
    FCONST_0
    FCONST_0
    INVOKESTATIC net/minecraft/client/renderer/GlStateManager.rotate (FFFF)V
   L9
    LINENUMBER 159 L9
    FLOAD 4
    LDC -41.0
    FMUL
    FCONST_0
    FCONST_0
    FCONST_1
    INVOKESTATIC net/minecraft/client/renderer/GlStateManager.rotate (FFFF)V
   L10
    LINENUMBER 160 L10
    FLOAD 4
    LDC 0.3
    FMUL
    LDC -1.1
    LDC 0.45
    INVOKESTATIC net/minecraft/client/renderer/GlStateManager.translate (FFF)V
   L11
    LINENUMBER 162 L11
    ALOAD 1
    GETSTATIC net/minecraft/util/EnumHandSide.RIGHT : Lnet/minecraft/util/EnumHandSide;
    IF_ACMPNE L12
   L13
    LINENUMBER 164 L13
    ALOAD 3
    ALOAD 0
    GETFIELD net/minecraft/client/renderer/ItemRenderer.mc : Lnet/minecraft/client/Minecraft;
    GETFIELD net/minecraft/client/Minecraft.thePlayer : Lnet/minecraft/client/entity/EntityPlayerSP;
    INVOKEVIRTUAL net/minecraft/client/renderer/entity/RenderPlayer.renderRightArm (Lnet/minecraft/client/entity/AbstractClientPlayer;)V
    GOTO L14
   L12
    LINENUMBER 168 L12
   FRAME FULL [net/minecraft/client/renderer/ItemRenderer net/minecraft/util/EnumHandSide net/minecraft/client/renderer/entity/Render net/minecraft/client/renderer/entity/RenderPlayer F] []
    ALOAD 3
    ALOAD 0
    GETFIELD net/minecraft/client/renderer/ItemRenderer.mc : Lnet/minecraft/client/Minecraft;
    GETFIELD net/minecraft/client/Minecraft.thePlayer : Lnet/minecraft/client/entity/EntityPlayerSP;
    INVOKEVIRTUAL net/minecraft/client/renderer/entity/RenderPlayer.renderLeftArm (Lnet/minecraft/client/entity/AbstractClientPlayer;)V
   L14
    LINENUMBER 171 L14
   FRAME FULL [net/minecraft/client/renderer/ItemRenderer net/minecraft/util/EnumHandSide net/minecraft/client/renderer/entity/Render net/minecraft/client/renderer/entity/RenderPlayer F] []
    INVOKESTATIC net/minecraft/client/renderer/GlStateManager.popMatrix ()V
   L15
    LINENUMBER 172 L15
    RETURN
   L16
    LOCALVARIABLE this Lnet/minecraft/client/renderer/ItemRenderer; L0 L16 0
    LOCALVARIABLE p_187455_1_ Lnet/minecraft/util/EnumHandSide; L0 L16 1
    LOCALVARIABLE render Lnet/minecraft/client/renderer/entity/Render; L2 L16 2
    // signature Lnet/minecraft/client/renderer/entity/Render<Lnet/minecraft/client/entity/AbstractClientPlayer;>;
    // declaration: net.minecraft.client.renderer.entity.Render<net.minecraft.client.entity.AbstractClientPlayer>
    LOCALVARIABLE renderplayer Lnet/minecraft/client/renderer/entity/RenderPlayer; L3 L16 3
    LOCALVARIABLE f F L7 L16 4
    MAXSTACK = 4
    MAXLOCALS = 5

  // access flags 0x2
  private renderMapFirstPersonSide(FLnet/minecraft/util/EnumHandSide;FLnet/minecraft/item/ItemStack;)V
   L0
    LINENUMBER 176 L0
    ALOAD 2
    GETSTATIC net/minecraft/util/EnumHandSide.RIGHT : Lnet/minecraft/util/EnumHandSide;
    IF_ACMPNE L1
    FCONST_1
    GOTO L2
   L1
   FRAME FULL [net/minecraft/client/renderer/ItemRenderer F net/minecraft/util/EnumHandSide F net/minecraft/item/ItemStack] []
    LDC -1.0
   L2
   FRAME FULL [net/minecraft/client/renderer/ItemRenderer F net/minecraft/util/EnumHandSide F net/minecraft/item/ItemStack] [F]
    FSTORE 5
   L3
    LINENUMBER 177 L3
    FLOAD 5
    LDC 0.125
    FMUL
    LDC -0.125
    FCONST_0
    INVOKESTATIC net/minecraft/client/renderer/GlStateManager.translate (FFF)V
   L4
    LINENUMBER 179 L4
    ALOAD 0
    GETFIELD net/minecraft/client/renderer/ItemRenderer.mc : Lnet/minecraft/client/Minecraft;
    GETFIELD net/minecraft/client/Minecraft.thePlayer : Lnet/minecraft/client/entity/EntityPlayerSP;
    INVOKEVIRTUAL net/minecraft/client/entity/EntityPlayerSP.isInvisible ()Z
    IFNE L5
   L6
    LINENUMBER 181 L6
    INVOKESTATIC net/minecraft/client/renderer/GlStateManager.pushMatrix ()V
   L7
    LINENUMBER 182 L7
    FLOAD 5
    LDC 10.0
    FMUL
    FCONST_0
    FCONST_0
    FCONST_1
    INVOKESTATIC net/minecraft/client/renderer/GlStateManager.rotate (FFFF)V
   L8
    LINENUMBER 183 L8
    ALOAD 0
    FLOAD 1
    FLOAD 3
    ALOAD 2
    INVOKESPECIAL net/minecraft/client/renderer/ItemRenderer.renderArmFirstPerson (FFLnet/minecraft/util/EnumHandSide;)V
   L9
    LINENUMBER 184 L9
    INVOKESTATIC net/minecraft/client/renderer/GlStateManager.popMatrix ()V
   L5
    LINENUMBER 187 L5
   FRAME FULL [net/minecraft/client/renderer/ItemRenderer F net/minecraft/util/EnumHandSide F net/minecraft/item/ItemStack F] []
    INVOKESTATIC net/minecraft/client/renderer/GlStateManager.pushMatrix ()V
   L10
    LINENUMBER 188 L10
    FLOAD 5
    LDC 0.51
    FMUL
    LDC -0.08
    FLOAD 1
    LDC -1.2
    FMUL
    FADD
    LDC -0.75
    INVOKESTATIC net/minecraft/client/renderer/GlStateManager.translate (FFF)V
   L11
    LINENUMBER 189 L11
    FLOAD 3
    INVOKESTATIC net/minecraft/util/math/MathHelper.sqrt_float (F)F
    FSTORE 6
   L12
    LINENUMBER 190 L12
    FLOAD 6
    LDC 3.1415927
    FMUL
    INVOKESTATIC net/minecraft/util/math/MathHelper.sin (F)F
    FSTORE 7
   L13
    LINENUMBER 191 L13
    LDC -0.5
    FLOAD 7
    FMUL
    FSTORE 8
   L14
    LINENUMBER 192 L14
    LDC 0.4
    FLOAD 6
    LDC 6.2831855
    FMUL
    INVOKESTATIC net/minecraft/util/math/MathHelper.sin (F)F
    FMUL
    FSTORE 9
   L15
    LINENUMBER 193 L15
    LDC -0.3
    FLOAD 3
    LDC 3.1415927
    FMUL
    INVOKESTATIC net/minecraft/util/math/MathHelper.sin (F)F
    FMUL
    FSTORE 10
   L16
    LINENUMBER 194 L16
    FLOAD 5
    FLOAD 8
    FMUL
    FLOAD 9
    LDC 0.3
    FLOAD 7
    FMUL
    FSUB
    FLOAD 10
    INVOKESTATIC net/minecraft/client/renderer/GlStateManager.translate (FFF)V
   L17
    LINENUMBER 195 L17
    FLOAD 7
    LDC -45.0
    FMUL
    FCONST_1
    FCONST_0
    FCONST_0
    INVOKESTATIC net/minecraft/client/renderer/GlStateManager.rotate (FFFF)V
   L18
    LINENUMBER 196 L18
    FLOAD 5
    FLOAD 7
    FMUL
    LDC -30.0
    FMUL
    FCONST_0
    FCONST_1
    FCONST_0
    INVOKESTATIC net/minecraft/client/renderer/GlStateManager.rotate (FFFF)V
   L19
    LINENUMBER 197 L19
    ALOAD 0
    ALOAD 4
    INVOKESPECIAL net/minecraft/client/renderer/ItemRenderer.renderMapFirstPerson (Lnet/minecraft/item/ItemStack;)V
   L20
    LINENUMBER 198 L20
    INVOKESTATIC net/minecraft/client/renderer/GlStateManager.popMatrix ()V
   L21
    LINENUMBER 199 L21
    RETURN
   L22
    LOCALVARIABLE this Lnet/minecraft/client/renderer/ItemRenderer; L0 L22 0
    LOCALVARIABLE p_187465_1_ F L0 L22 1
    LOCALVARIABLE p_187465_2_ Lnet/minecraft/util/EnumHandSide; L0 L22 2
    LOCALVARIABLE p_187465_3_ F L0 L22 3
    LOCALVARIABLE p_187465_4_ Lnet/minecraft/item/ItemStack; L0 L22 4
    LOCALVARIABLE f F L3 L22 5
    LOCALVARIABLE f1 F L12 L22 6
    LOCALVARIABLE f2 F L13 L22 7
    LOCALVARIABLE f3 F L14 L22 8
    LOCALVARIABLE f4 F L15 L22 9
    LOCALVARIABLE f5 F L16 L22 10
    MAXSTACK = 4
    MAXLOCALS = 11

  // access flags 0x2
  private renderMapFirstPerson(FFF)V
   L0
    LINENUMBER 203 L0
    FLOAD 3
    INVOKESTATIC net/minecraft/util/math/MathHelper.sqrt_float (F)F
    FSTORE 4
   L1
    LINENUMBER 204 L1
    LDC -0.2
    FLOAD 3
    LDC 3.1415927
    FMUL
    INVOKESTATIC net/minecraft/util/math/MathHelper.sin (F)F
    FMUL
    FSTORE 5
   L2
    LINENUMBER 205 L2
    LDC -0.4
    FLOAD 4
    LDC 3.1415927
    FMUL
    INVOKESTATIC net/minecraft/util/math/MathHelper.sin (F)F
    FMUL
    FSTORE 6
   L3
    LINENUMBER 206 L3
    FCONST_0
    FLOAD 5
    FNEG
    FCONST_2
    FDIV
    FLOAD 6
    INVOKESTATIC net/minecraft/client/renderer/GlStateManager.translate (FFF)V
   L4
    LINENUMBER 207 L4
    ALOAD 0
    FLOAD 1
    INVOKESPECIAL net/minecraft/client/renderer/ItemRenderer.getMapAngleFromPitch (F)F
    FSTORE 7
   L5
    LINENUMBER 208 L5
    FCONST_0
    LDC 0.04
    FLOAD 2
    LDC -1.2
    FMUL
    FADD
    FLOAD 7
    LDC -0.5
    FMUL
    FADD
    LDC -0.72
    INVOKESTATIC net/minecraft/client/renderer/GlStateManager.translate (FFF)V
   L6
    LINENUMBER 209 L6
    FLOAD 7
    LDC -85.0
    FMUL
    FCONST_1
    FCONST_0
    FCONST_0
    INVOKESTATIC net/minecraft/client/renderer/GlStateManager.rotate (FFFF)V
   L7
    LINENUMBER 210 L7
    ALOAD 0
    INVOKESPECIAL net/minecraft/client/renderer/ItemRenderer.renderArms ()V
   L8
    LINENUMBER 211 L8
    FLOAD 4
    LDC 3.1415927
    FMUL
    INVOKESTATIC net/minecraft/util/math/MathHelper.sin (F)F
    FSTORE 8
   L9
    LINENUMBER 212 L9
    FLOAD 8
    LDC 20.0
    FMUL
    FCONST_1
    FCONST_0
    FCONST_0
    INVOKESTATIC net/minecraft/client/renderer/GlStateManager.rotate (FFFF)V
   L10
    LINENUMBER 213 L10
    FCONST_2
    FCONST_2
    FCONST_2
    INVOKESTATIC net/minecraft/client/renderer/GlStateManager.scale (FFF)V
   L11
    LINENUMBER 214 L11
    ALOAD 0
    ALOAD 0
    GETFIELD net/minecraft/client/renderer/ItemRenderer.itemStackMainHand : Lnet/minecraft/item/ItemStack;
    INVOKESPECIAL net/minecraft/client/renderer/ItemRenderer.renderMapFirstPerson (Lnet/minecraft/item/ItemStack;)V
   L12
    LINENUMBER 215 L12
    RETURN
   L13
    LOCALVARIABLE this Lnet/minecraft/client/renderer/ItemRenderer; L0 L13 0
    LOCALVARIABLE p_187463_1_ F L0 L13 1
    LOCALVARIABLE p_187463_2_ F L0 L13 2
    LOCALVARIABLE p_187463_3_ F L0 L13 3
    LOCALVARIABLE f F L1 L13 4
    LOCALVARIABLE f1 F L2 L13 5
    LOCALVARIABLE f2 F L3 L13 6
    LOCALVARIABLE f3 F L5 L13 7
    LOCALVARIABLE f4 F L9 L13 8
    MAXSTACK = 4
    MAXLOCALS = 9

  // access flags 0x2
  private renderMapFirstPerson(Lnet/minecraft/item/ItemStack;)V
    ALOAD 1
    ICONST_0
    INVOKESTATIC codechicken/lib/render/item/map/MapRenderRegistry.shouldHandle (Lnet/minecraft/item/ItemStack;Z)Z
    IFEQ L0
    ALOAD 1
    ICONST_0
    INVOKESTATIC codechicken/lib/render/item/map/MapRenderRegistry.handleRender (Lnet/minecraft/item/ItemStack;Z)V
    RETURN
   L0
    LINENUMBER 219 L0
   FRAME FULL [net/minecraft/client/renderer/ItemRenderer net/minecraft/item/ItemStack] []
    LDC 180.0
    FCONST_0
    FCONST_1
    FCONST_0
    INVOKESTATIC net/minecraft/client/renderer/GlStateManager.rotate (FFFF)V
   L1
    LINENUMBER 220 L1
    LDC 180.0
    FCONST_0
    FCONST_0
    FCONST_1
    INVOKESTATIC net/minecraft/client/renderer/GlStateManager.rotate (FFFF)V
   L2
    LINENUMBER 221 L2
    LDC 0.38
    LDC 0.38
    LDC 0.38
    INVOKESTATIC net/minecraft/client/renderer/GlStateManager.scale (FFF)V
   L3
    LINENUMBER 222 L3
    INVOKESTATIC net/minecraft/client/renderer/GlStateManager.disableLighting ()V
   L4
    LINENUMBER 223 L4
    ALOAD 0
    GETFIELD net/minecraft/client/renderer/ItemRenderer.mc : Lnet/minecraft/client/Minecraft;
    INVOKEVIRTUAL net/minecraft/client/Minecraft.getTextureManager ()Lnet/minecraft/client/renderer/texture/TextureManager;
    GETSTATIC net/minecraft/client/renderer/ItemRenderer.RES_MAP_BACKGROUND : Lnet/minecraft/util/ResourceLocation;
    INVOKEVIRTUAL net/minecraft/client/renderer/texture/TextureManager.bindTexture (Lnet/minecraft/util/ResourceLocation;)V
   L5
    LINENUMBER 224 L5
    INVOKESTATIC net/minecraft/client/renderer/Tessellator.getInstance ()Lnet/minecraft/client/renderer/Tessellator;
    ASTORE 2
   L6
    LINENUMBER 225 L6
    ALOAD 2
    INVOKEVIRTUAL net/minecraft/client/renderer/Tessellator.getBuffer ()Lnet/minecraft/client/renderer/VertexBuffer;
    ASTORE 3
   L7
    LINENUMBER 226 L7
    LDC -0.5
    LDC -0.5
    FCONST_0
    INVOKESTATIC net/minecraft/client/renderer/GlStateManager.translate (FFF)V
   L8
    LINENUMBER 227 L8
    LDC 0.0078125
    LDC 0.0078125
    LDC 0.0078125
    INVOKESTATIC net/minecraft/client/renderer/GlStateManager.scale (FFF)V
   L9
    LINENUMBER 228 L9
    ALOAD 3
    BIPUSH 7
    GETSTATIC net/minecraft/client/renderer/vertex/DefaultVertexFormats.POSITION_TEX : Lnet/minecraft/client/renderer/vertex/VertexFormat;
    INVOKEVIRTUAL net/minecraft/client/renderer/VertexBuffer.begin (ILnet/minecraft/client/renderer/vertex/VertexFormat;)V
   L10
    LINENUMBER 229 L10
    ALOAD 3
    LDC -7.0
    LDC 135.0
    DCONST_0
    INVOKEVIRTUAL net/minecraft/client/renderer/VertexBuffer.pos (DDD)Lnet/minecraft/client/renderer/VertexBuffer;
    DCONST_0
    DCONST_1
    INVOKEVIRTUAL net/minecraft/client/renderer/VertexBuffer.tex (DD)Lnet/minecraft/client/renderer/VertexBuffer;
    INVOKEVIRTUAL net/minecraft/client/renderer/VertexBuffer.endVertex ()V
   L11
    LINENUMBER 230 L11
    ALOAD 3
    LDC 135.0
    LDC 135.0
    DCONST_0
    INVOKEVIRTUAL net/minecraft/client/renderer/VertexBuffer.pos (DDD)Lnet/minecraft/client/renderer/VertexBuffer;
    DCONST_1
    DCONST_1
    INVOKEVIRTUAL net/minecraft/client/renderer/VertexBuffer.tex (DD)Lnet/minecraft/client/renderer/VertexBuffer;
    INVOKEVIRTUAL net/minecraft/client/renderer/VertexBuffer.endVertex ()V
   L12
    LINENUMBER 231 L12
    ALOAD 3
    LDC 135.0
    LDC -7.0
    DCONST_0
    INVOKEVIRTUAL net/minecraft/client/renderer/VertexBuffer.pos (DDD)Lnet/minecraft/client/renderer/VertexBuffer;
    DCONST_1
    DCONST_0
    INVOKEVIRTUAL net/minecraft/client/renderer/VertexBuffer.tex (DD)Lnet/minecraft/client/renderer/VertexBuffer;
    INVOKEVIRTUAL net/minecraft/client/renderer/VertexBuffer.endVertex ()V
   L13
    LINENUMBER 232 L13
    ALOAD 3
    LDC -7.0
    LDC -7.0
    DCONST_0
    INVOKEVIRTUAL net/minecraft/client/renderer/VertexBuffer.pos (DDD)Lnet/minecraft/client/renderer/VertexBuffer;
    DCONST_0
    DCONST_0
    INVOKEVIRTUAL net/minecraft/client/renderer/VertexBuffer.tex (DD)Lnet/minecraft/client/renderer/VertexBuffer;
    INVOKEVIRTUAL net/minecraft/client/renderer/VertexBuffer.endVertex ()V
   L14
    LINENUMBER 233 L14
    ALOAD 2
    INVOKEVIRTUAL net/minecraft/client/renderer/Tessellator.draw ()V
   L15
    LINENUMBER 234 L15
    GETSTATIC net/minecraft/init/Items.FILLED_MAP : Lnet/minecraft/item/ItemMap;
    ALOAD 1
    ALOAD 0
    GETFIELD net/minecraft/client/renderer/ItemRenderer.mc : Lnet/minecraft/client/Minecraft;
    GETFIELD net/minecraft/client/Minecraft.theWorld : Lnet/minecraft/client/multiplayer/WorldClient;
    INVOKEVIRTUAL net/minecraft/item/ItemMap.getMapData (Lnet/minecraft/item/ItemStack;Lnet/minecraft/world/World;)Lnet/minecraft/world/storage/MapData;
    ASTORE 4
   L16
    LINENUMBER 236 L16
    ALOAD 4
    IFNULL L17
   L18
    LINENUMBER 238 L18
    ALOAD 0
    GETFIELD net/minecraft/client/renderer/ItemRenderer.mc : Lnet/minecraft/client/Minecraft;
    GETFIELD net/minecraft/client/Minecraft.entityRenderer : Lnet/minecraft/client/renderer/EntityRenderer;
    INVOKEVIRTUAL net/minecraft/client/renderer/EntityRenderer.getMapItemRenderer ()Lnet/minecraft/client/gui/MapItemRenderer;
    ALOAD 4
    ICONST_0
    INVOKEVIRTUAL net/minecraft/client/gui/MapItemRenderer.renderMap (Lnet/minecraft/world/storage/MapData;Z)V
   L17
    LINENUMBER 241 L17
   FRAME FULL [net/minecraft/client/renderer/ItemRenderer net/minecraft/item/ItemStack net/minecraft/client/renderer/Tessellator net/minecraft/client/renderer/VertexBuffer net/minecraft/world/storage/MapData] []
    INVOKESTATIC net/minecraft/client/renderer/GlStateManager.enableLighting ()V
   L19
    LINENUMBER 242 L19
    RETURN
   L20
    LOCALVARIABLE this Lnet/minecraft/client/renderer/ItemRenderer; L0 L20 0
    LOCALVARIABLE stack Lnet/minecraft/item/ItemStack; L0 L20 1
    LOCALVARIABLE tessellator Lnet/minecraft/client/renderer/Tessellator; L6 L20 2
    LOCALVARIABLE vertexbuffer Lnet/minecraft/client/renderer/VertexBuffer; L7 L20 3
    LOCALVARIABLE mapdata Lnet/minecraft/world/storage/MapData; L16 L20 4
    MAXSTACK = 7
    MAXLOCALS = 5

  // access flags 0x2
  private renderArmFirstPerson(FFLnet/minecraft/util/EnumHandSide;)V
   L0
    LINENUMBER 246 L0
    ALOAD 3
    GETSTATIC net/minecraft/util/EnumHandSide.LEFT : Lnet/minecraft/util/EnumHandSide;
    IF_ACMPEQ L1
    ICONST_1
    GOTO L2
   L1
   FRAME FULL [net/minecraft/client/renderer/ItemRenderer F F net/minecraft/util/EnumHandSide] []
    ICONST_0
   L2
   FRAME FULL [net/minecraft/client/renderer/ItemRenderer F F net/minecraft/util/EnumHandSide] [I]
    ISTORE 4
   L3
    LINENUMBER 247 L3
    ILOAD 4
    IFEQ L4
    FCONST_1
    GOTO L5
   L4
   FRAME FULL [net/minecraft/client/renderer/ItemRenderer F F net/minecraft/util/EnumHandSide I] []
    LDC -1.0
   L5
   FRAME FULL [net/minecraft/client/renderer/ItemRenderer F F net/minecraft/util/EnumHandSide I] [F]
    FSTORE 5
   L6
    LINENUMBER 248 L6
    FLOAD 2
    INVOKESTATIC net/minecraft/util/math/MathHelper.sqrt_float (F)F
    FSTORE 6
   L7
    LINENUMBER 249 L7
    LDC -0.3
    FLOAD 6
    LDC 3.1415927
    FMUL
    INVOKESTATIC net/minecraft/util/math/MathHelper.sin (F)F
    FMUL
    FSTORE 7
   L8
    LINENUMBER 250 L8
    LDC 0.4
    FLOAD 6
    LDC 6.2831855
    FMUL
    INVOKESTATIC net/minecraft/util/math/MathHelper.sin (F)F
    FMUL
    FSTORE 8
   L9
    LINENUMBER 251 L9
    LDC -0.4
    FLOAD 2
    LDC 3.1415927
    FMUL
    INVOKESTATIC net/minecraft/util/math/MathHelper.sin (F)F
    FMUL
    FSTORE 9
   L10
    LINENUMBER 252 L10
    FLOAD 5
    FLOAD 7
    LDC 0.64000005
    FADD
    FMUL
    FLOAD 8
    LDC -0.6
    FADD
    FLOAD 1
    LDC -0.6
    FMUL
    FADD
    FLOAD 9
    LDC -0.71999997
    FADD
    INVOKESTATIC net/minecraft/client/renderer/GlStateManager.translate (FFF)V
   L11
    LINENUMBER 253 L11
    FLOAD 5
    LDC 45.0
    FMUL
    FCONST_0
    FCONST_1
    FCONST_0
    INVOKESTATIC net/minecraft/client/renderer/GlStateManager.rotate (FFFF)V
   L12
    LINENUMBER 254 L12
    FLOAD 2
    FLOAD 2
    FMUL
    LDC 3.1415927
    FMUL
    INVOKESTATIC net/minecraft/util/math/MathHelper.sin (F)F
    FSTORE 10
   L13
    LINENUMBER 255 L13
    FLOAD 6
    LDC 3.1415927
    FMUL
    INVOKESTATIC net/minecraft/util/math/MathHelper.sin (F)F
    FSTORE 11
   L14
    LINENUMBER 256 L14
    FLOAD 5
    FLOAD 11
    FMUL
    LDC 70.0
    FMUL
    FCONST_0
    FCONST_1
    FCONST_0
    INVOKESTATIC net/minecraft/client/renderer/GlStateManager.rotate (FFFF)V
   L15
    LINENUMBER 257 L15
    FLOAD 5
    FLOAD 10
    FMUL
    LDC -20.0
    FMUL
    FCONST_0
    FCONST_0
    FCONST_1
    INVOKESTATIC net/minecraft/client/renderer/GlStateManager.rotate (FFFF)V
   L16
    LINENUMBER 258 L16
    ALOAD 0
    GETFIELD net/minecraft/client/renderer/ItemRenderer.mc : Lnet/minecraft/client/Minecraft;
    GETFIELD net/minecraft/client/Minecraft.thePlayer : Lnet/minecraft/client/entity/EntityPlayerSP;
    ASTORE 12
   L17
    LINENUMBER 259 L17
    ALOAD 0
    GETFIELD net/minecraft/client/renderer/ItemRenderer.mc : Lnet/minecraft/client/Minecraft;
    INVOKEVIRTUAL net/minecraft/client/Minecraft.getTextureManager ()Lnet/minecraft/client/renderer/texture/TextureManager;
    ALOAD 12
    INVOKEVIRTUAL net/minecraft/client/entity/AbstractClientPlayer.getLocationSkin ()Lnet/minecraft/util/ResourceLocation;
    INVOKEVIRTUAL net/minecraft/client/renderer/texture/TextureManager.bindTexture (Lnet/minecraft/util/ResourceLocation;)V
   L18
    LINENUMBER 260 L18
    FLOAD 5
    LDC -1.0
    FMUL
    LDC 3.6
    LDC 3.5
    INVOKESTATIC net/minecraft/client/renderer/GlStateManager.translate (FFF)V
   L19
    LINENUMBER 261 L19
    FLOAD 5
    LDC 120.0
    FMUL
    FCONST_0
    FCONST_0
    FCONST_1
    INVOKESTATIC net/minecraft/client/renderer/GlStateManager.rotate (FFFF)V
   L20
    LINENUMBER 262 L20
    LDC 200.0
    FCONST_1
    FCONST_0
    FCONST_0
    INVOKESTATIC net/minecraft/client/renderer/GlStateManager.rotate (FFFF)V
   L21
    LINENUMBER 263 L21
    FLOAD 5
    LDC -135.0
    FMUL
    FCONST_0
    FCONST_1
    FCONST_0
    INVOKESTATIC net/minecraft/client/renderer/GlStateManager.rotate (FFFF)V
   L22
    LINENUMBER 264 L22
    FLOAD 5
    LDC 5.6
    FMUL
    FCONST_0
    FCONST_0
    INVOKESTATIC net/minecraft/client/renderer/GlStateManager.translate (FFF)V
   L23
    LINENUMBER 265 L23
    ALOAD 0
    GETFIELD net/minecraft/client/renderer/ItemRenderer.renderManager : Lnet/minecraft/client/renderer/entity/RenderManager;
    ALOAD 12
    INVOKEVIRTUAL net/minecraft/client/renderer/entity/RenderManager.getEntityRenderObject (Lnet/minecraft/entity/Entity;)Lnet/minecraft/client/renderer/entity/Render;
    CHECKCAST net/minecraft/client/renderer/entity/RenderPlayer
    ASTORE 13
   L24
    LINENUMBER 266 L24
    INVOKESTATIC net/minecraft/client/renderer/GlStateManager.disableCull ()V
   L25
    LINENUMBER 268 L25
    ILOAD 4
    IFEQ L26
   L27
    LINENUMBER 270 L27
    ALOAD 13
    ALOAD 12
    INVOKEVIRTUAL net/minecraft/client/renderer/entity/RenderPlayer.renderRightArm (Lnet/minecraft/client/entity/AbstractClientPlayer;)V
    GOTO L28
   L26
    LINENUMBER 274 L26
   FRAME FULL [net/minecraft/client/renderer/ItemRenderer F F net/minecraft/util/EnumHandSide I F F F F F F F net/minecraft/client/entity/EntityPlayerSP net/minecraft/client/renderer/entity/RenderPlayer] []
    ALOAD 13
    ALOAD 12
    INVOKEVIRTUAL net/minecraft/client/renderer/entity/RenderPlayer.renderLeftArm (Lnet/minecraft/client/entity/AbstractClientPlayer;)V
   L28
    LINENUMBER 277 L28
   FRAME FULL [net/minecraft/client/renderer/ItemRenderer F F net/minecraft/util/EnumHandSide I F F F F F F F net/minecraft/client/entity/EntityPlayerSP net/minecraft/client/renderer/entity/RenderPlayer] []
    INVOKESTATIC net/minecraft/client/renderer/GlStateManager.enableCull ()V
   L29
    LINENUMBER 278 L29
    RETURN
   L30
    LOCALVARIABLE this Lnet/minecraft/client/renderer/ItemRenderer; L0 L30 0
    LOCALVARIABLE p_187456_1_ F L0 L30 1
    LOCALVARIABLE p_187456_2_ F L0 L30 2
    LOCALVARIABLE p_187456_3_ Lnet/minecraft/util/EnumHandSide; L0 L30 3
    LOCALVARIABLE flag Z L3 L30 4
    LOCALVARIABLE f F L6 L30 5
    LOCALVARIABLE f1 F L7 L30 6
    LOCALVARIABLE f2 F L8 L30 7
    LOCALVARIABLE f3 F L9 L30 8
    LOCALVARIABLE f4 F L10 L30 9
    LOCALVARIABLE f5 F L13 L30 10
    LOCALVARIABLE f6 F L14 L30 11
    LOCALVARIABLE abstractclientplayer Lnet/minecraft/client/entity/AbstractClientPlayer; L17 L30 12
    LOCALVARIABLE renderplayer Lnet/minecraft/client/renderer/entity/RenderPlayer; L24 L30 13
    MAXSTACK = 4
    MAXLOCALS = 14

  // access flags 0x2
  private transformEatFirstPerson(FLnet/minecraft/util/EnumHandSide;Lnet/minecraft/item/ItemStack;)V
   L0
    LINENUMBER 282 L0
    ALOAD 0
    GETFIELD net/minecraft/client/renderer/ItemRenderer.mc : Lnet/minecraft/client/Minecraft;
    GETFIELD net/minecraft/client/Minecraft.thePlayer : Lnet/minecraft/client/entity/EntityPlayerSP;
    INVOKEVIRTUAL net/minecraft/client/entity/EntityPlayerSP.getItemInUseCount ()I
    I2F
    FLOAD 1
    FSUB
    FCONST_1
    FADD
    FSTORE 4
   L1
    LINENUMBER 283 L1
    FLOAD 4
    ALOAD 3
    INVOKEVIRTUAL net/minecraft/item/ItemStack.getMaxItemUseDuration ()I
    I2F
    FDIV
    FSTORE 5
   L2
    LINENUMBER 285 L2
    FLOAD 5
    LDC 0.8
    FCMPG
    IFGE L3
   L4
    LINENUMBER 287 L4
    FLOAD 4
    LDC 4.0
    FDIV
    LDC 3.1415927
    FMUL
    INVOKESTATIC net/minecraft/util/math/MathHelper.cos (F)F
    LDC 0.1
    FMUL
    INVOKESTATIC net/minecraft/util/math/MathHelper.abs (F)F
    FSTORE 6
   L5
    LINENUMBER 288 L5
    FCONST_0
    FLOAD 6
    FCONST_0
    INVOKESTATIC net/minecraft/client/renderer/GlStateManager.translate (FFF)V
   L3
    LINENUMBER 291 L3
   FRAME FULL [net/minecraft/client/renderer/ItemRenderer F net/minecraft/util/EnumHandSide net/minecraft/item/ItemStack F F] []
    FCONST_1
    FLOAD 5
    F2D
    LDC 27.0
    INVOKESTATIC java/lang/Math.pow (DD)D
    D2F
    FSUB
    FSTORE 6
   L6
    LINENUMBER 292 L6
    ALOAD 2
    GETSTATIC net/minecraft/util/EnumHandSide.RIGHT : Lnet/minecraft/util/EnumHandSide;
    IF_ACMPNE L7
    ICONST_1
    GOTO L8
   L7
   FRAME FULL [net/minecraft/client/renderer/ItemRenderer F net/minecraft/util/EnumHandSide net/minecraft/item/ItemStack F F F] []
    ICONST_M1
   L8
   FRAME FULL [net/minecraft/client/renderer/ItemRenderer F net/minecraft/util/EnumHandSide net/minecraft/item/ItemStack F F F] [I]
    ISTORE 7
   L9
    LINENUMBER 293 L9
    FLOAD 6
    LDC 0.6
    FMUL
    ILOAD 7
    I2F
    FMUL
    FLOAD 6
    LDC -0.5
    FMUL
    FLOAD 6
    FCONST_0
    FMUL
    INVOKESTATIC net/minecraft/client/renderer/GlStateManager.translate (FFF)V
   L10
    LINENUMBER 294 L10
    ILOAD 7
    I2F
    FLOAD 6
    FMUL
    LDC 90.0
    FMUL
    FCONST_0
    FCONST_1
    FCONST_0
    INVOKESTATIC net/minecraft/client/renderer/GlStateManager.rotate (FFFF)V
   L11
    LINENUMBER 295 L11
    FLOAD 6
    LDC 10.0
    FMUL
    FCONST_1
    FCONST_0
    FCONST_0
    INVOKESTATIC net/minecraft/client/renderer/GlStateManager.rotate (FFFF)V
   L12
    LINENUMBER 296 L12
    ILOAD 7
    I2F
    FLOAD 6
    FMUL
    LDC 30.0
    FMUL
    FCONST_0
    FCONST_0
    FCONST_1
    INVOKESTATIC net/minecraft/client/renderer/GlStateManager.rotate (FFFF)V
   L13
    LINENUMBER 297 L13
    RETURN
   L14
    LOCALVARIABLE f2 F L5 L3 6
    LOCALVARIABLE this Lnet/minecraft/client/renderer/ItemRenderer; L0 L14 0
    LOCALVARIABLE p_187454_1_ F L0 L14 1
    LOCALVARIABLE p_187454_2_ Lnet/minecraft/util/EnumHandSide; L0 L14 2
    LOCALVARIABLE p_187454_3_ Lnet/minecraft/item/ItemStack; L0 L14 3
    LOCALVARIABLE f F L1 L14 4
    LOCALVARIABLE f1 F L2 L14 5
    LOCALVARIABLE f3 F L6 L14 6
    LOCALVARIABLE i I L9 L14 7
    MAXSTACK = 5
    MAXLOCALS = 8

  // access flags 0x2
  private transformFirstPerson(Lnet/minecraft/util/EnumHandSide;F)V
   L0
    LINENUMBER 301 L0
    ALOAD 1
    GETSTATIC net/minecraft/util/EnumHandSide.RIGHT : Lnet/minecraft/util/EnumHandSide;
    IF_ACMPNE L1
    ICONST_1
    GOTO L2
   L1
   FRAME FULL [net/minecraft/client/renderer/ItemRenderer net/minecraft/util/EnumHandSide F] []
    ICONST_M1
   L2
   FRAME FULL [net/minecraft/client/renderer/ItemRenderer net/minecraft/util/EnumHandSide F] [I]
    ISTORE 3
   L3
    LINENUMBER 302 L3
    FLOAD 2
    FLOAD 2
    FMUL
    LDC 3.1415927
    FMUL
    INVOKESTATIC net/minecraft/util/math/MathHelper.sin (F)F
    FSTORE 4
   L4
    LINENUMBER 303 L4
    ILOAD 3
    I2F
    LDC 45.0
    FLOAD 4
    LDC -20.0
    FMUL
    FADD
    FMUL
    FCONST_0
    FCONST_1
    FCONST_0
    INVOKESTATIC net/minecraft/client/renderer/GlStateManager.rotate (FFFF)V
   L5
    LINENUMBER 304 L5
    FLOAD 2
    INVOKESTATIC net/minecraft/util/math/MathHelper.sqrt_float (F)F
    LDC 3.1415927
    FMUL
    INVOKESTATIC net/minecraft/util/math/MathHelper.sin (F)F
    FSTORE 5
   L6
    LINENUMBER 305 L6
    ILOAD 3
    I2F
    FLOAD 5
    FMUL
    LDC -20.0
    FMUL
    FCONST_0
    FCONST_0
    FCONST_1
    INVOKESTATIC net/minecraft/client/renderer/GlStateManager.rotate (FFFF)V
   L7
    LINENUMBER 306 L7
    FLOAD 5
    LDC -80.0
    FMUL
    FCONST_1
    FCONST_0
    FCONST_0
    INVOKESTATIC net/minecraft/client/renderer/GlStateManager.rotate (FFFF)V
   L8
    LINENUMBER 307 L8
    ILOAD 3
    I2F
    LDC -45.0
    FMUL
    FCONST_0
    FCONST_1
    FCONST_0
    INVOKESTATIC net/minecraft/client/renderer/GlStateManager.rotate (FFFF)V
   L9
    LINENUMBER 308 L9
    RETURN
   L10
    LOCALVARIABLE this Lnet/minecraft/client/renderer/ItemRenderer; L0 L10 0
    LOCALVARIABLE p_187453_1_ Lnet/minecraft/util/EnumHandSide; L0 L10 1
    LOCALVARIABLE p_187453_2_ F L0 L10 2
    LOCALVARIABLE i I L3 L10 3
    LOCALVARIABLE f F L4 L10 4
    LOCALVARIABLE f1 F L6 L10 5
    MAXSTACK = 4
    MAXLOCALS = 6

  // access flags 0x2
  private transformSideFirstPerson(Lnet/minecraft/util/EnumHandSide;F)V
   L0
    LINENUMBER 312 L0
    ALOAD 1
    GETSTATIC net/minecraft/util/EnumHandSide.RIGHT : Lnet/minecraft/util/EnumHandSide;
    IF_ACMPNE L1
    ICONST_1
    GOTO L2
   L1
   FRAME FULL [net/minecraft/client/renderer/ItemRenderer net/minecraft/util/EnumHandSide F] []
    ICONST_M1
   L2
   FRAME FULL [net/minecraft/client/renderer/ItemRenderer net/minecraft/util/EnumHandSide F] [I]
    ISTORE 3
   L3
    LINENUMBER 313 L3
    ILOAD 3
    I2F
    LDC 0.56
    FMUL
    LDC -0.52
    FLOAD 2
    LDC -0.6
    FMUL
    FADD
    LDC -0.72
    INVOKESTATIC net/minecraft/client/renderer/GlStateManager.translate (FFF)V
   L4
    LINENUMBER 314 L4
    RETURN
   L5
    LOCALVARIABLE this Lnet/minecraft/client/renderer/ItemRenderer; L0 L5 0
    LOCALVARIABLE p_187459_1_ Lnet/minecraft/util/EnumHandSide; L0 L5 1
    LOCALVARIABLE p_187459_2_ F L0 L5 2
    LOCALVARIABLE i I L3 L5 3
    MAXSTACK = 4
    MAXLOCALS = 4

  // access flags 0x1
  public renderItemInFirstPerson(F)V
   L0
    LINENUMBER 321 L0
    ALOAD 0
    GETFIELD net/minecraft/client/renderer/ItemRenderer.mc : Lnet/minecraft/client/Minecraft;
    GETFIELD net/minecraft/client/Minecraft.thePlayer : Lnet/minecraft/client/entity/EntityPlayerSP;
    ASTORE 2
   L1
    LINENUMBER 322 L1
    ALOAD 2
    FLOAD 1
    INVOKEVIRTUAL net/minecraft/client/entity/AbstractClientPlayer.getSwingProgress (F)F
    FSTORE 3
   L2
    LINENUMBER 323 L2
    ALOAD 2
    GETFIELD net/minecraft/client/entity/AbstractClientPlayer.swingingHand : Lnet/minecraft/util/EnumHand;
    GETSTATIC net/minecraft/util/EnumHand.MAIN_HAND : Lnet/minecraft/util/EnumHand;
    INVOKESTATIC com/google/common/base/Objects.firstNonNull (Ljava/lang/Object;Ljava/lang/Object;)Ljava/lang/Object;
    CHECKCAST net/minecraft/util/EnumHand
    ASTORE 4
   L3
    LINENUMBER 324 L3
    ALOAD 2
    GETFIELD net/minecraft/client/entity/AbstractClientPlayer.prevRotationPitch : F
    ALOAD 2
    GETFIELD net/minecraft/client/entity/AbstractClientPlayer.rotationPitch : F
    ALOAD 2
    GETFIELD net/minecraft/client/entity/AbstractClientPlayer.prevRotationPitch : F
    FSUB
    FLOAD 1
    FMUL
    FADD
    FSTORE 5
   L4
    LINENUMBER 325 L4
    ALOAD 2
    GETFIELD net/minecraft/client/entity/AbstractClientPlayer.prevRotationYaw : F
    ALOAD 2
    GETFIELD net/minecraft/client/entity/AbstractClientPlayer.rotationYaw : F
    ALOAD 2
    GETFIELD net/minecraft/client/entity/AbstractClientPlayer.prevRotationYaw : F
    FSUB
    FLOAD 1
    FMUL
    FADD
    FSTORE 6
   L5
    LINENUMBER 326 L5
    ICONST_1
    ISTORE 7
   L6
    LINENUMBER 327 L6
    ICONST_1
    ISTORE 8
   L7
    LINENUMBER 329 L7
    ALOAD 2
    INVOKEVIRTUAL net/minecraft/client/entity/AbstractClientPlayer.isHandActive ()Z
    IFEQ L8
   L9
    LINENUMBER 331 L9
    ALOAD 2
    INVOKEVIRTUAL net/minecraft/client/entity/AbstractClientPlayer.getActiveItemStack ()Lnet/minecraft/item/ItemStack;
    ASTORE 9
   L10
    LINENUMBER 333 L10
    ALOAD 9
    IFNULL L8
    ALOAD 9
    INVOKEVIRTUAL net/minecraft/item/ItemStack.getItem ()Lnet/minecraft/item/Item;
    GETSTATIC net/minecraft/init/Items.BOW : Lnet/minecraft/item/ItemBow;
    IF_ACMPNE L8
   L11
    LINENUMBER 335 L11
    ALOAD 2
    INVOKEVIRTUAL net/minecraft/client/entity/AbstractClientPlayer.getActiveHand ()Lnet/minecraft/util/EnumHand;
    ASTORE 10
   L12
    LINENUMBER 336 L12
    ALOAD 10
    GETSTATIC net/minecraft/util/EnumHand.MAIN_HAND : Lnet/minecraft/util/EnumHand;
    IF_ACMPNE L13
    ICONST_1
    GOTO L14
   L13
   FRAME FULL [net/minecraft/client/renderer/ItemRenderer F net/minecraft/client/entity/EntityPlayerSP F net/minecraft/util/EnumHand F F I I net/minecraft/item/ItemStack net/minecraft/util/EnumHand] []
    ICONST_0
   L14
   FRAME FULL [net/minecraft/client/renderer/ItemRenderer F net/minecraft/client/entity/EntityPlayerSP F net/minecraft/util/EnumHand F F I I net/minecraft/item/ItemStack net/minecraft/util/EnumHand] [I]
    ISTORE 7
   L15
    LINENUMBER 337 L15
    ILOAD 7
    IFNE L16
    ICONST_1
    GOTO L17
   L16
   FRAME FULL [net/minecraft/client/renderer/ItemRenderer F net/minecraft/client/entity/EntityPlayerSP F net/minecraft/util/EnumHand F F I I net/minecraft/item/ItemStack net/minecraft/util/EnumHand] []
    ICONST_0
   L17
   FRAME FULL [net/minecraft/client/renderer/ItemRenderer F net/minecraft/client/entity/EntityPlayerSP F net/minecraft/util/EnumHand F F I I net/minecraft/item/ItemStack net/minecraft/util/EnumHand] [I]
    ISTORE 8
   L8
    LINENUMBER 341 L8
   FRAME FULL [net/minecraft/client/renderer/ItemRenderer F net/minecraft/client/entity/EntityPlayerSP F net/minecraft/util/EnumHand F F I I] []
    ALOAD 0
    FLOAD 5
    FLOAD 6
    INVOKESPECIAL net/minecraft/client/renderer/ItemRenderer.rotateArroundXAndY (FF)V
   L18
    LINENUMBER 342 L18
    ALOAD 0
    INVOKESPECIAL net/minecraft/client/renderer/ItemRenderer.setLightmap ()V
   L19
    LINENUMBER 343 L19
    ALOAD 0
    FLOAD 1
    INVOKESPECIAL net/minecraft/client/renderer/ItemRenderer.rotateArm (F)V
   L20
    LINENUMBER 344 L20
    INVOKESTATIC net/minecraft/client/renderer/GlStateManager.enableRescaleNormal ()V
   L21
    LINENUMBER 346 L21
    ILOAD 7
    IFEQ L22
   L23
    LINENUMBER 348 L23
    ALOAD 4
    GETSTATIC net/minecraft/util/EnumHand.MAIN_HAND : Lnet/minecraft/util/EnumHand;
    IF_ACMPNE L24
    FLOAD 3
    GOTO L25
   L24
   FRAME FULL [net/minecraft/client/renderer/ItemRenderer F net/minecraft/client/entity/EntityPlayerSP F net/minecraft/util/EnumHand F F I I] []
    FCONST_0
   L25
   FRAME FULL [net/minecraft/client/renderer/ItemRenderer F net/minecraft/client/entity/EntityPlayerSP F net/minecraft/util/EnumHand F F I I] [F]
    FSTORE 9
   L26
    LINENUMBER 349 L26
    FCONST_1
    ALOAD 0
    GETFIELD net/minecraft/client/renderer/ItemRenderer.prevEquippedProgressMainHand : F
    ALOAD 0
    GETFIELD net/minecraft/client/renderer/ItemRenderer.equippedProgressMainHand : F
    ALOAD 0
    GETFIELD net/minecraft/client/renderer/ItemRenderer.prevEquippedProgressMainHand : F
    FSUB
    FLOAD 1
    FMUL
    FADD
    FSUB
    FSTORE 10
   L27
    LINENUMBER 350 L27
    GETSTATIC net/minecraft/util/EnumHand.MAIN_HAND : Lnet/minecraft/util/EnumHand;
    FLOAD 1
    FLOAD 5
    FLOAD 9
    FLOAD 10
    ALOAD 0
    GETFIELD net/minecraft/client/renderer/ItemRenderer.itemStackMainHand : Lnet/minecraft/item/ItemStack;
    INVOKESTATIC net/minecraftforge/client/ForgeHooksClient.renderSpecificFirstPersonHand (Lnet/minecraft/util/EnumHand;FFFFLnet/minecraft/item/ItemStack;)Z
    IFNE L22
   L28
    LINENUMBER 351 L28
    ALOAD 0
    ALOAD 2
    FLOAD 1
    FLOAD 5
    GETSTATIC net/minecraft/util/EnumHand.MAIN_HAND : Lnet/minecraft/util/EnumHand;
    FLOAD 9
    ALOAD 0
    GETFIELD net/minecraft/client/renderer/ItemRenderer.itemStackMainHand : Lnet/minecraft/item/ItemStack;
    FLOAD 10
    INVOKEVIRTUAL net/minecraft/client/renderer/ItemRenderer.renderItemInFirstPerson (Lnet/minecraft/client/entity/AbstractClientPlayer;FFLnet/minecraft/util/EnumHand;FLnet/minecraft/item/ItemStack;F)V
   L22
    LINENUMBER 354 L22
   FRAME FULL [net/minecraft/client/renderer/ItemRenderer F net/minecraft/client/entity/EntityPlayerSP F net/minecraft/util/EnumHand F F I I] []
    ILOAD 8
    IFEQ L29
   L30
    LINENUMBER 356 L30
    ALOAD 4
    GETSTATIC net/minecraft/util/EnumHand.OFF_HAND : Lnet/minecraft/util/EnumHand;
    IF_ACMPNE L31
    FLOAD 3
    GOTO L32
   L31
   FRAME FULL [net/minecraft/client/renderer/ItemRenderer F net/minecraft/client/entity/EntityPlayerSP F net/minecraft/util/EnumHand F F I I] []
    FCONST_0
   L32
   FRAME FULL [net/minecraft/client/renderer/ItemRenderer F net/minecraft/client/entity/EntityPlayerSP F net/minecraft/util/EnumHand F F I I] [F]
    FSTORE 9
   L33
    LINENUMBER 357 L33
    FCONST_1
    ALOAD 0
    GETFIELD net/minecraft/client/renderer/ItemRenderer.prevEquippedProgressOffHand : F
    ALOAD 0
    GETFIELD net/minecraft/client/renderer/ItemRenderer.equippedProgressOffHand : F
    ALOAD 0
    GETFIELD net/minecraft/client/renderer/ItemRenderer.prevEquippedProgressOffHand : F
    FSUB
    FLOAD 1
    FMUL
    FADD
    FSUB
    FSTORE 10
   L34
    LINENUMBER 358 L34
    GETSTATIC net/minecraft/util/EnumHand.OFF_HAND : Lnet/minecraft/util/EnumHand;
    FLOAD 1
    FLOAD 5
    FLOAD 9
    FLOAD 10
    ALOAD 0
    GETFIELD net/minecraft/client/renderer/ItemRenderer.itemStackOffHand : Lnet/minecraft/item/ItemStack;
    INVOKESTATIC net/minecraftforge/client/ForgeHooksClient.renderSpecificFirstPersonHand (Lnet/minecraft/util/EnumHand;FFFFLnet/minecraft/item/ItemStack;)Z
    IFNE L29
   L35
    LINENUMBER 359 L35
    ALOAD 0
    ALOAD 2
    FLOAD 1
    FLOAD 5
    GETSTATIC net/minecraft/util/EnumHand.OFF_HAND : Lnet/minecraft/util/EnumHand;
    FLOAD 9
    ALOAD 0
    GETFIELD net/minecraft/client/renderer/ItemRenderer.itemStackOffHand : Lnet/minecraft/item/ItemStack;
    FLOAD 10
    INVOKEVIRTUAL net/minecraft/client/renderer/ItemRenderer.renderItemInFirstPerson (Lnet/minecraft/client/entity/AbstractClientPlayer;FFLnet/minecraft/util/EnumHand;FLnet/minecraft/item/ItemStack;F)V
   L29
    LINENUMBER 362 L29
   FRAME FULL [net/minecraft/client/renderer/ItemRenderer F net/minecraft/client/entity/EntityPlayerSP F net/minecraft/util/EnumHand F F I I] []
    INVOKESTATIC net/minecraft/client/renderer/GlStateManager.disableRescaleNormal ()V
   L36
    LINENUMBER 363 L36
    INVOKESTATIC net/minecraft/client/renderer/RenderHelper.disableStandardItemLighting ()V
   L37
    LINENUMBER 364 L37
    RETURN
   L38
    LOCALVARIABLE enumhand1 Lnet/minecraft/util/EnumHand; L12 L8 10
    LOCALVARIABLE itemstack Lnet/minecraft/item/ItemStack; L10 L8 9
    LOCALVARIABLE f3 F L26 L22 9
    LOCALVARIABLE f5 F L27 L22 10
    LOCALVARIABLE f4 F L33 L29 9
    LOCALVARIABLE f6 F L34 L29 10
    LOCALVARIABLE this Lnet/minecraft/client/renderer/ItemRenderer; L0 L38 0
    LOCALVARIABLE partialTicks F L0 L38 1
    LOCALVARIABLE abstractclientplayer Lnet/minecraft/client/entity/AbstractClientPlayer; L1 L38 2
    LOCALVARIABLE f F L2 L38 3
    LOCALVARIABLE enumhand Lnet/minecraft/util/EnumHand; L3 L38 4
    LOCALVARIABLE f1 F L4 L38 5
    LOCALVARIABLE f2 F L5 L38 6
    LOCALVARIABLE flag Z L6 L38 7
    LOCALVARIABLE flag1 Z L7 L38 8
    MAXSTACK = 8
    MAXLOCALS = 11

  // access flags 0x1
  public renderItemInFirstPerson(Lnet/minecraft/client/entity/AbstractClientPlayer;FFLnet/minecraft/util/EnumHand;FLnet/minecraft/item/ItemStack;F)V
    @Ljavax/annotation/Nullable;() // parameter 5
   L0
    LINENUMBER 368 L0
    ALOAD 4
    GETSTATIC net/minecraft/util/EnumHand.MAIN_HAND : Lnet/minecraft/util/EnumHand;
    IF_ACMPNE L1
    ICONST_1
    GOTO L2
   L1
   FRAME FULL [net/minecraft/client/renderer/ItemRenderer net/minecraft/client/entity/AbstractClientPlayer F F net/minecraft/util/EnumHand F net/minecraft/item/ItemStack F] []
    ICONST_0
   L2
   FRAME FULL [net/minecraft/client/renderer/ItemRenderer net/minecraft/client/entity/AbstractClientPlayer F F net/minecraft/util/EnumHand F net/minecraft/item/ItemStack F] [I]
    ISTORE 8
   L3
    LINENUMBER 369 L3
    ILOAD 8
    IFEQ L4
    ALOAD 1
    INVOKEVIRTUAL net/minecraft/client/entity/AbstractClientPlayer.getPrimaryHand ()Lnet/minecraft/util/EnumHandSide;
    GOTO L5
   L4
   FRAME FULL [net/minecraft/client/renderer/ItemRenderer net/minecraft/client/entity/AbstractClientPlayer F F net/minecraft/util/EnumHand F net/minecraft/item/ItemStack F I] []
    ALOAD 1
    INVOKEVIRTUAL net/minecraft/client/entity/AbstractClientPlayer.getPrimaryHand ()Lnet/minecraft/util/EnumHandSide;
    INVOKEVIRTUAL net/minecraft/util/EnumHandSide.opposite ()Lnet/minecraft/util/EnumHandSide;
   L5
   FRAME FULL [net/minecraft/client/renderer/ItemRenderer net/minecraft/client/entity/AbstractClientPlayer F F net/minecraft/util/EnumHand F net/minecraft/item/ItemStack F I] [net/minecraft/util/EnumHandSide]
    ASTORE 9
   L6
    LINENUMBER 370 L6
    INVOKESTATIC net/minecraft/client/renderer/GlStateManager.pushMatrix ()V
   L7
    LINENUMBER 372 L7
    ALOAD 6
    IFNONNULL L8
   L9
    LINENUMBER 374 L9
    ILOAD 8
    IFEQ L10
    ALOAD 1
    INVOKEVIRTUAL net/minecraft/client/entity/AbstractClientPlayer.isInvisible ()Z
    IFNE L10
   L11
    LINENUMBER 376 L11
    ALOAD 0
    FLOAD 7
    FLOAD 5
    ALOAD 9
    INVOKESPECIAL net/minecraft/client/renderer/ItemRenderer.renderArmFirstPerson (FFLnet/minecraft/util/EnumHandSide;)V
    GOTO L10
   L8
    LINENUMBER 379 L8
   FRAME FULL [net/minecraft/client/renderer/ItemRenderer net/minecraft/client/entity/AbstractClientPlayer F F net/minecraft/util/EnumHand F net/minecraft/item/ItemStack F I net/minecraft/util/EnumHandSide] []
    ALOAD 6
    INVOKEVIRTUAL net/minecraft/item/ItemStack.getItem ()Lnet/minecraft/item/Item;
    INSTANCEOF net/minecraft/item/ItemMap
    IFEQ L12
   L13
    LINENUMBER 381 L13
    ILOAD 8
    IFEQ L14
    ALOAD 0
    GETFIELD net/minecraft/client/renderer/ItemRenderer.itemStackOffHand : Lnet/minecraft/item/ItemStack;
    IFNONNULL L14
   L15
    LINENUMBER 383 L15
    ALOAD 0
    FLOAD 3
    FLOAD 7
    FLOAD 5
    INVOKESPECIAL net/minecraft/client/renderer/ItemRenderer.renderMapFirstPerson (FFF)V
    GOTO L10
   L14
    LINENUMBER 387 L14
   FRAME FULL [net/minecraft/client/renderer/ItemRenderer net/minecraft/client/entity/AbstractClientPlayer F F net/minecraft/util/EnumHand F net/minecraft/item/ItemStack F I net/minecraft/util/EnumHandSide] []
    ALOAD 0
    FLOAD 7
    ALOAD 9
    FLOAD 5
    ALOAD 6
    INVOKESPECIAL net/minecraft/client/renderer/ItemRenderer.renderMapFirstPersonSide (FLnet/minecraft/util/EnumHandSide;FLnet/minecraft/item/ItemStack;)V
    GOTO L10
   L12
    LINENUMBER 392 L12
   FRAME FULL [net/minecraft/client/renderer/ItemRenderer net/minecraft/client/entity/AbstractClientPlayer F F net/minecraft/util/EnumHand F net/minecraft/item/ItemStack F I net/minecraft/util/EnumHandSide] []
    ALOAD 9
    GETSTATIC net/minecraft/util/EnumHandSide.RIGHT : Lnet/minecraft/util/EnumHandSide;
    IF_ACMPNE L16
    ICONST_1
    GOTO L17
   L16
   FRAME FULL [net/minecraft/client/renderer/ItemRenderer net/minecraft/client/entity/AbstractClientPlayer F F net/minecraft/util/EnumHand F net/minecraft/item/ItemStack F I net/minecraft/util/EnumHandSide] []
    ICONST_0
   L17
   FRAME FULL [net/minecraft/client/renderer/ItemRenderer net/minecraft/client/entity/AbstractClientPlayer F F net/minecraft/util/EnumHand F net/minecraft/item/ItemStack F I net/minecraft/util/EnumHandSide] [I]
    ISTORE 10
   L18
    LINENUMBER 394 L18
    ALOAD 1
    INVOKEVIRTUAL net/minecraft/client/entity/AbstractClientPlayer.isHandActive ()Z
    IFEQ L19
    ALOAD 1
    INVOKEVIRTUAL net/minecraft/client/entity/AbstractClientPlayer.getItemInUseCount ()I
    IFLE L19
    ALOAD 1
    INVOKEVIRTUAL net/minecraft/client/entity/AbstractClientPlayer.getActiveHand ()Lnet/minecraft/util/EnumHand;
    ALOAD 4
    IF_ACMPNE L19
   L20
    LINENUMBER 396 L20
    ILOAD 10
    IFEQ L21
    ICONST_1
    GOTO L22
   L21
   FRAME FULL [net/minecraft/client/renderer/ItemRenderer net/minecraft/client/entity/AbstractClientPlayer F F net/minecraft/util/EnumHand F net/minecraft/item/ItemStack F I net/minecraft/util/EnumHandSide I] []
    ICONST_M1
   L22
   FRAME FULL [net/minecraft/client/renderer/ItemRenderer net/minecraft/client/entity/AbstractClientPlayer F F net/minecraft/util/EnumHand F net/minecraft/item/ItemStack F I net/minecraft/util/EnumHandSide I] [I]
    ISTORE 11
   L23
    LINENUMBER 398 L23
    GETSTATIC net/minecraft/client/renderer/ItemRenderer$1.$SwitchMap$net$minecraft$item$EnumAction : [I
    ALOAD 6
    INVOKEVIRTUAL net/minecraft/item/ItemStack.getItemUseAction ()Lnet/minecraft/item/EnumAction;
    INVOKEVIRTUAL net/minecraft/item/EnumAction.ordinal ()I
    IALOAD
    TABLESWITCH
      1: L24
      2: L25
      3: L25
      4: L26
      5: L27
      default: L28
   L24
    LINENUMBER 401 L24
   FRAME FULL [net/minecraft/client/renderer/ItemRenderer net/minecraft/client/entity/AbstractClientPlayer F F net/minecraft/util/EnumHand F net/minecraft/item/ItemStack F I net/minecraft/util/EnumHandSide I I] []
    ALOAD 0
    ALOAD 9
    FLOAD 7
    INVOKESPECIAL net/minecraft/client/renderer/ItemRenderer.transformSideFirstPerson (Lnet/minecraft/util/EnumHandSide;F)V
   L29
    LINENUMBER 402 L29
    GOTO L28
   L25
    LINENUMBER 405 L25
   FRAME FULL [net/minecraft/client/renderer/ItemRenderer net/minecraft/client/entity/AbstractClientPlayer F F net/minecraft/util/EnumHand F net/minecraft/item/ItemStack F I net/minecraft/util/EnumHandSide I I] []
    ALOAD 0
    FLOAD 2
    ALOAD 9
    ALOAD 6
    INVOKESPECIAL net/minecraft/client/renderer/ItemRenderer.transformEatFirstPerson (FLnet/minecraft/util/EnumHandSide;Lnet/minecraft/item/ItemStack;)V
   L30
    LINENUMBER 406 L30
    ALOAD 0
    ALOAD 9
    FLOAD 7
    INVOKESPECIAL net/minecraft/client/renderer/ItemRenderer.transformSideFirstPerson (Lnet/minecraft/util/EnumHandSide;F)V
   L31
    LINENUMBER 407 L31
    GOTO L28
   L26
    LINENUMBER 409 L26
   FRAME FULL [net/minecraft/client/renderer/ItemRenderer net/minecraft/client/entity/AbstractClientPlayer F F net/minecraft/util/EnumHand F net/minecraft/item/ItemStack F I net/minecraft/util/EnumHandSide I I] []
    ALOAD 0
    ALOAD 9
    FLOAD 7
    INVOKESPECIAL net/minecraft/client/renderer/ItemRenderer.transformSideFirstPerson (Lnet/minecraft/util/EnumHandSide;F)V
   L32
    LINENUMBER 410 L32
    GOTO L28
   L27
    LINENUMBER 412 L27
   FRAME FULL [net/minecraft/client/renderer/ItemRenderer net/minecraft/client/entity/AbstractClientPlayer F F net/minecraft/util/EnumHand F net/minecraft/item/ItemStack F I net/minecraft/util/EnumHandSide I I] []
    ALOAD 0
    ALOAD 9
    FLOAD 7
    INVOKESPECIAL net/minecraft/client/renderer/ItemRenderer.transformSideFirstPerson (Lnet/minecraft/util/EnumHandSide;F)V
   L33
    LINENUMBER 413 L33
    ILOAD 11
    I2F
    LDC -0.2785682
    FMUL
    LDC 0.18344387
    LDC 0.15731531
    INVOKESTATIC net/minecraft/client/renderer/GlStateManager.translate (FFF)V
   L34
    LINENUMBER 414 L34
    LDC -13.935
    FCONST_1
    FCONST_0
    FCONST_0
    INVOKESTATIC net/minecraft/client/renderer/GlStateManager.rotate (FFFF)V
   L35
    LINENUMBER 415 L35
    ILOAD 11
    I2F
    LDC 35.3
    FMUL
    FCONST_0
    FCONST_1
    FCONST_0
    INVOKESTATIC net/minecraft/client/renderer/GlStateManager.rotate (FFFF)V
   L36
    LINENUMBER 416 L36
    ILOAD 11
    I2F
    LDC -9.785
    FMUL
    FCONST_0
    FCONST_0
    FCONST_1
    INVOKESTATIC net/minecraft/client/renderer/GlStateManager.rotate (FFFF)V
   L37
    LINENUMBER 417 L37
    ALOAD 6
    INVOKEVIRTUAL net/minecraft/item/ItemStack.getMaxItemUseDuration ()I
    I2F
    ALOAD 0
    GETFIELD net/minecraft/client/renderer/ItemRenderer.mc : Lnet/minecraft/client/Minecraft;
    GETFIELD net/minecraft/client/Minecraft.thePlayer : Lnet/minecraft/client/entity/EntityPlayerSP;
    INVOKEVIRTUAL net/minecraft/client/entity/EntityPlayerSP.getItemInUseCount ()I
    I2F
    FLOAD 2
    FSUB
    FCONST_1
    FADD
    FSUB
    FSTORE 12
   L38
    LINENUMBER 418 L38
    FLOAD 12
    LDC 20.0
    FDIV
    FSTORE 13
   L39
    LINENUMBER 419 L39
    FLOAD 13
    FLOAD 13
    FMUL
    FLOAD 13
    FCONST_2
    FMUL
    FADD
    LDC 3.0
    FDIV
    FSTORE 13
   L40
    LINENUMBER 421 L40
    FLOAD 13
    FCONST_1
    FCMPL
    IFLE L41
   L42
    LINENUMBER 423 L42
    FCONST_1
    FSTORE 13
   L41
    LINENUMBER 426 L41
   FRAME FULL [net/minecraft/client/renderer/ItemRenderer net/minecraft/client/entity/AbstractClientPlayer F F net/minecraft/util/EnumHand F net/minecraft/item/ItemStack F I net/minecraft/util/EnumHandSide I I F F] []
    FLOAD 13
    LDC 0.1
    FCMPL
    IFLE L43
   L44
    LINENUMBER 428 L44
    FLOAD 12
    LDC 0.1
    FSUB
    LDC 1.3
    FMUL
    INVOKESTATIC net/minecraft/util/math/MathHelper.sin (F)F
    FSTORE 14
   L45
    LINENUMBER 429 L45
    FLOAD 13
    LDC 0.1
    FSUB
    FSTORE 15
   L46
    LINENUMBER 430 L46
    FLOAD 14
    FLOAD 15
    FMUL
    FSTORE 16
   L47
    LINENUMBER 431 L47
    FLOAD 16
    FCONST_0
    FMUL
    FLOAD 16
    LDC 0.004
    FMUL
    FLOAD 16
    FCONST_0
    FMUL
    INVOKESTATIC net/minecraft/client/renderer/GlStateManager.translate (FFF)V
   L43
    LINENUMBER 434 L43
   FRAME FULL [net/minecraft/client/renderer/ItemRenderer net/minecraft/client/entity/AbstractClientPlayer F F net/minecraft/util/EnumHand F net/minecraft/item/ItemStack F I net/minecraft/util/EnumHandSide I I F F] []
    FLOAD 13
    FCONST_0
    FMUL
    FLOAD 13
    FCONST_0
    FMUL
    FLOAD 13
    LDC 0.04
    FMUL
    INVOKESTATIC net/minecraft/client/renderer/GlStateManager.translate (FFF)V
   L48
    LINENUMBER 435 L48
    FCONST_1
    FCONST_1
    FCONST_1
    FLOAD 13
    LDC 0.2
    FMUL
    FADD
    INVOKESTATIC net/minecraft/client/renderer/GlStateManager.scale (FFF)V
   L49
    LINENUMBER 436 L49
    ILOAD 11
    I2F
    LDC 45.0
    FMUL
    FCONST_0
    LDC -1.0
    FCONST_0
    INVOKESTATIC net/minecraft/client/renderer/GlStateManager.rotate (FFFF)V
   L28
    LINENUMBER 438 L28
   FRAME FULL [net/minecraft/client/renderer/ItemRenderer net/minecraft/client/entity/AbstractClientPlayer F F net/minecraft/util/EnumHand F net/minecraft/item/ItemStack F I net/minecraft/util/EnumHandSide I I] []
    GOTO L50
   L19
    LINENUMBER 441 L19
   FRAME FULL [net/minecraft/client/renderer/ItemRenderer net/minecraft/client/entity/AbstractClientPlayer F F net/minecraft/util/EnumHand F net/minecraft/item/ItemStack F I net/minecraft/util/EnumHandSide I] []
    LDC -0.4
    FLOAD 5
    INVOKESTATIC net/minecraft/util/math/MathHelper.sqrt_float (F)F
    LDC 3.1415927
    FMUL
    INVOKESTATIC net/minecraft/util/math/MathHelper.sin (F)F
    FMUL
    FSTORE 11
   L51
    LINENUMBER 442 L51
    LDC 0.2
    FLOAD 5
    INVOKESTATIC net/minecraft/util/math/MathHelper.sqrt_float (F)F
    LDC 6.2831855
    FMUL
    INVOKESTATIC net/minecraft/util/math/MathHelper.sin (F)F
    FMUL
    FSTORE 12
   L52
    LINENUMBER 443 L52
    LDC -0.2
    FLOAD 5
    LDC 3.1415927
    FMUL
    INVOKESTATIC net/minecraft/util/math/MathHelper.sin (F)F
    FMUL
    FSTORE 13
   L53
    LINENUMBER 444 L53
    ILOAD 10
    IFEQ L54
    ICONST_1
    GOTO L55
   L54
   FRAME FULL [net/minecraft/client/renderer/ItemRenderer net/minecraft/client/entity/AbstractClientPlayer F F net/minecraft/util/EnumHand F net/minecraft/item/ItemStack F I net/minecraft/util/EnumHandSide I F F F] []
    ICONST_M1
   L55
   FRAME FULL [net/minecraft/client/renderer/ItemRenderer net/minecraft/client/entity/AbstractClientPlayer F F net/minecraft/util/EnumHand F net/minecraft/item/ItemStack F I net/minecraft/util/EnumHandSide I F F F] [I]
    ISTORE 14
   L56
    LINENUMBER 445 L56
    ILOAD 14
    I2F
    FLOAD 11
    FMUL
    FLOAD 12
    FLOAD 13
    INVOKESTATIC net/minecraft/client/renderer/GlStateManager.translate (FFF)V
   L57
    LINENUMBER 446 L57
    ALOAD 0
    ALOAD 9
    FLOAD 7
    INVOKESPECIAL net/minecraft/client/renderer/ItemRenderer.transformSideFirstPerson (Lnet/minecraft/util/EnumHandSide;F)V
   L58
    LINENUMBER 447 L58
    ALOAD 0
    ALOAD 9
    FLOAD 5
    INVOKESPECIAL net/minecraft/client/renderer/ItemRenderer.transformFirstPerson (Lnet/minecraft/util/EnumHandSide;F)V
   L50
    LINENUMBER 450 L50
   FRAME FULL [net/minecraft/client/renderer/ItemRenderer net/minecraft/client/entity/AbstractClientPlayer F F net/minecraft/util/EnumHand F net/minecraft/item/ItemStack F I net/minecraft/util/EnumHandSide I] []
    ALOAD 0
    ALOAD 1
    ALOAD 6
    ILOAD 10
    IFEQ L59
    GETSTATIC net/minecraft/client/renderer/block/model/ItemCameraTransforms$TransformType.FIRST_PERSON_RIGHT_HAND : Lnet/minecraft/client/renderer/block/model/ItemCameraTransforms$TransformType;
    GOTO L60
   L59
   FRAME FULL [net/minecraft/client/renderer/ItemRenderer net/minecraft/client/entity/AbstractClientPlayer F F net/minecraft/util/EnumHand F net/minecraft/item/ItemStack F I net/minecraft/util/EnumHandSide I] [net/minecraft/client/renderer/ItemRenderer net/minecraft/client/entity/AbstractClientPlayer net/minecraft/item/ItemStack]
    GETSTATIC net/minecraft/client/renderer/block/model/ItemCameraTransforms$TransformType.FIRST_PERSON_LEFT_HAND : Lnet/minecraft/client/renderer/block/model/ItemCameraTransforms$TransformType;
   L60
   FRAME FULL [net/minecraft/client/renderer/ItemRenderer net/minecraft/client/entity/AbstractClientPlayer F F net/minecraft/util/EnumHand F net/minecraft/item/ItemStack F I net/minecraft/util/EnumHandSide I] [net/minecraft/client/renderer/ItemRenderer net/minecraft/client/entity/AbstractClientPlayer net/minecraft/item/ItemStack net/minecraft/client/renderer/block/model/ItemCameraTransforms$TransformType]
    ILOAD 10
    IFNE L61
    ICONST_1
    GOTO L62
   L61
   FRAME FULL [net/minecraft/client/renderer/ItemRenderer net/minecraft/client/entity/AbstractClientPlayer F F net/minecraft/util/EnumHand F net/minecraft/item/ItemStack F I net/minecraft/util/EnumHandSide I] [net/minecraft/client/renderer/ItemRenderer net/minecraft/client/entity/AbstractClientPlayer net/minecraft/item/ItemStack net/minecraft/client/renderer/block/model/ItemCameraTransforms$TransformType]
    ICONST_0
   L62
   FRAME FULL [net/minecraft/client/renderer/ItemRenderer net/minecraft/client/entity/AbstractClientPlayer F F net/minecraft/util/EnumHand F net/minecraft/item/ItemStack F I net/minecraft/util/EnumHandSide I] [net/minecraft/client/renderer/ItemRenderer net/minecraft/client/entity/AbstractClientPlayer net/minecraft/item/ItemStack net/minecraft/client/renderer/block/model/ItemCameraTransforms$TransformType I]
    INVOKEVIRTUAL net/minecraft/client/renderer/ItemRenderer.renderItemSide (Lnet/minecraft/entity/EntityLivingBase;Lnet/minecraft/item/ItemStack;Lnet/minecraft/client/renderer/block/model/ItemCameraTransforms$TransformType;Z)V
   L10
    LINENUMBER 453 L10
   FRAME FULL [net/minecraft/client/renderer/ItemRenderer net/minecraft/client/entity/AbstractClientPlayer F F net/minecraft/util/EnumHand F net/minecraft/item/ItemStack F I net/minecraft/util/EnumHandSide] []
    INVOKESTATIC net/minecraft/client/renderer/GlStateManager.popMatrix ()V
   L63
    LINENUMBER 454 L63
    RETURN
   L64
    LOCALVARIABLE f7 F L45 L43 14
    LOCALVARIABLE f3 F L46 L43 15
    LOCALVARIABLE f4 F L47 L43 16
    LOCALVARIABLE f5 F L38 L28 12
    LOCALVARIABLE f6 F L39 L28 13
    LOCALVARIABLE j I L23 L28 11
    LOCALVARIABLE f F L51 L50 11
    LOCALVARIABLE f1 F L52 L50 12
    LOCALVARIABLE f2 F L53 L50 13
    LOCALVARIABLE i I L56 L50 14
    LOCALVARIABLE flag1 Z L18 L10 10
    LOCALVARIABLE this Lnet/minecraft/client/renderer/ItemRenderer; L0 L64 0
    LOCALVARIABLE p_187457_1_ Lnet/minecraft/client/entity/AbstractClientPlayer; L0 L64 1
    LOCALVARIABLE p_187457_2_ F L0 L64 2
    LOCALVARIABLE p_187457_3_ F L0 L64 3
    LOCALVARIABLE p_187457_4_ Lnet/minecraft/util/EnumHand; L0 L64 4
    LOCALVARIABLE p_187457_5_ F L0 L64 5
    LOCALVARIABLE p_187457_6_ Lnet/minecraft/item/ItemStack; L0 L64 6
    LOCALVARIABLE p_187457_7_ F L0 L64 7
    LOCALVARIABLE flag Z L3 L64 8
    LOCALVARIABLE enumhandside Lnet/minecraft/util/EnumHandSide; L6 L64 9
    MAXSTACK = 5
    MAXLOCALS = 17

  // access flags 0x1
  public renderOverlays(F)V
   L0
    LINENUMBER 461 L0
    INVOKESTATIC net/minecraft/client/renderer/GlStateManager.disableAlpha ()V
   L1
    LINENUMBER 463 L1
    ALOAD 0
    GETFIELD net/minecraft/client/renderer/ItemRenderer.mc : Lnet/minecraft/client/Minecraft;
    GETFIELD net/minecraft/client/Minecraft.thePlayer : Lnet/minecraft/client/entity/EntityPlayerSP;
    INVOKEVIRTUAL net/minecraft/client/entity/EntityPlayerSP.isEntityInsideOpaqueBlock ()Z
    IFEQ L2
   L3
    LINENUMBER 465 L3
    ALOAD 0
    GETFIELD net/minecraft/client/renderer/ItemRenderer.mc : Lnet/minecraft/client/Minecraft;
    GETFIELD net/minecraft/client/Minecraft.theWorld : Lnet/minecraft/client/multiplayer/WorldClient;
    NEW net/minecraft/util/math/BlockPos
    DUP
    ALOAD 0
    GETFIELD net/minecraft/client/renderer/ItemRenderer.mc : Lnet/minecraft/client/Minecraft;
    GETFIELD net/minecraft/client/Minecraft.thePlayer : Lnet/minecraft/client/entity/EntityPlayerSP;
    INVOKESPECIAL net/minecraft/util/math/BlockPos.<init> (Lnet/minecraft/entity/Entity;)V
    INVOKEVIRTUAL net/minecraft/client/multiplayer/WorldClient.getBlockState (Lnet/minecraft/util/math/BlockPos;)Lnet/minecraft/block/state/IBlockState;
    ASTORE 2
   L4
    LINENUMBER 466 L4
    NEW net/minecraft/util/math/BlockPos
    DUP
    ALOAD 0
    GETFIELD net/minecraft/client/renderer/ItemRenderer.mc : Lnet/minecraft/client/Minecraft;
    GETFIELD net/minecraft/client/Minecraft.thePlayer : Lnet/minecraft/client/entity/EntityPlayerSP;
    INVOKESPECIAL net/minecraft/util/math/BlockPos.<init> (Lnet/minecraft/entity/Entity;)V
    ASTORE 3
   L5
    LINENUMBER 467 L5
    ALOAD 0
    GETFIELD net/minecraft/client/renderer/ItemRenderer.mc : Lnet/minecraft/client/Minecraft;
    GETFIELD net/minecraft/client/Minecraft.thePlayer : Lnet/minecraft/client/entity/EntityPlayerSP;
    ASTORE 4
   L6
    LINENUMBER 469 L6
    ICONST_0
    ISTORE 5
   L7
   FRAME FULL [net/minecraft/client/renderer/ItemRenderer F net/minecraft/block/state/IBlockState net/minecraft/util/math/BlockPos net/minecraft/client/entity/EntityPlayerSP I] []
    ILOAD 5
    BIPUSH 8
    IF_ICMPGE L8
   L9
    LINENUMBER 471 L9
    ALOAD 4
    GETFIELD net/minecraft/entity/player/EntityPlayer.posX : D
    ILOAD 5
    ICONST_0
    ISHR
    ICONST_2
    IREM
    I2F
    LDC 0.5
    FSUB
    ALOAD 4
    GETFIELD net/minecraft/entity/player/EntityPlayer.width : F
    FMUL
    LDC 0.8
    FMUL
    F2D
    DADD
    DSTORE 6
   L10
    LINENUMBER 472 L10
    ALOAD 4
    GETFIELD net/minecraft/entity/player/EntityPlayer.posY : D
    ILOAD 5
    ICONST_1
    ISHR
    ICONST_2
    IREM
    I2F
    LDC 0.5
    FSUB
    LDC 0.1
    FMUL
    F2D
    DADD
    DSTORE 8
   L11
    LINENUMBER 473 L11
    ALOAD 4
    GETFIELD net/minecraft/entity/player/EntityPlayer.posZ : D
    ILOAD 5
    ICONST_2
    ISHR
    ICONST_2
    IREM
    I2F
    LDC 0.5
    FSUB
    ALOAD 4
    GETFIELD net/minecraft/entity/player/EntityPlayer.width : F
    FMUL
    LDC 0.8
    FMUL
    F2D
    DADD
    DSTORE 10
   L12
    LINENUMBER 474 L12
    NEW net/minecraft/util/math/BlockPos
    DUP
    DLOAD 6
    DLOAD 8
    ALOAD 4
    INVOKEVIRTUAL net/minecraft/entity/player/EntityPlayer.getEyeHeight ()F
    F2D
    DADD
    DLOAD 10
    INVOKESPECIAL net/minecraft/util/math/BlockPos.<init> (DDD)V
    ASTORE 12
   L13
    LINENUMBER 475 L13
    ALOAD 0
    GETFIELD net/minecraft/client/renderer/ItemRenderer.mc : Lnet/minecraft/client/Minecraft;
    GETFIELD net/minecraft/client/Minecraft.theWorld : Lnet/minecraft/client/multiplayer/WorldClient;
    ALOAD 12
    INVOKEVIRTUAL net/minecraft/client/multiplayer/WorldClient.getBlockState (Lnet/minecraft/util/math/BlockPos;)Lnet/minecraft/block/state/IBlockState;
    ASTORE 13
   L14
    LINENUMBER 477 L14
    ALOAD 13
    INVOKEINTERFACE net/minecraft/block/state/IBlockState.getBlock ()Lnet/minecraft/block/Block;
    INVOKEVIRTUAL net/minecraft/block/Block.isVisuallyOpaque ()Z
    IFEQ L15
   L16
    LINENUMBER 479 L16
    ALOAD 13
    ASTORE 2
   L17
    LINENUMBER 480 L17
    ALOAD 12
    ASTORE 3
   L15
    LINENUMBER 469 L15
   FRAME FULL [net/minecraft/client/renderer/ItemRenderer F net/minecraft/block/state/IBlockState net/minecraft/util/math/BlockPos net/minecraft/client/entity/EntityPlayerSP I D D D net/minecraft/util/math/BlockPos net/minecraft/block/state/IBlockState] []
    IINC 5 1
    GOTO L7
   L8
    LINENUMBER 484 L8
   FRAME FULL [net/minecraft/client/renderer/ItemRenderer F net/minecraft/block/state/IBlockState net/minecraft/util/math/BlockPos net/minecraft/client/entity/EntityPlayerSP I] []
    ALOAD 2
    INVOKEINTERFACE net/minecraft/block/state/IBlockState.getRenderType ()Lnet/minecraft/util/EnumBlockRenderType;
    GETSTATIC net/minecraft/util/EnumBlockRenderType.INVISIBLE : Lnet/minecraft/util/EnumBlockRenderType;
    IF_ACMPEQ L2
   L18
    LINENUMBER 486 L18
    ALOAD 0
    GETFIELD net/minecraft/client/renderer/ItemRenderer.mc : Lnet/minecraft/client/Minecraft;
    GETFIELD net/minecraft/client/Minecraft.thePlayer : Lnet/minecraft/client/entity/EntityPlayerSP;
    FLOAD 1
    GETSTATIC net/minecraftforge/client/event/RenderBlockOverlayEvent$OverlayType.BLOCK : Lnet/minecraftforge/client/event/RenderBlockOverlayEvent$OverlayType;
    ALOAD 2
    ALOAD 3
    INVOKESTATIC net/minecraftforge/event/ForgeEventFactory.renderBlockOverlay (Lnet/minecraft/entity/player/EntityPlayer;FLnet/minecraftforge/client/event/RenderBlockOverlayEvent$OverlayType;Lnet/minecraft/block/state/IBlockState;Lnet/minecraft/util/math/BlockPos;)Z
    IFNE L2
   L19
    LINENUMBER 487 L19
    ALOAD 0
    FLOAD 1
    ALOAD 0
    GETFIELD net/minecraft/client/renderer/ItemRenderer.mc : Lnet/minecraft/client/Minecraft;
    INVOKEVIRTUAL net/minecraft/client/Minecraft.getBlockRendererDispatcher ()Lnet/minecraft/client/renderer/BlockRendererDispatcher;
    INVOKEVIRTUAL net/minecraft/client/renderer/BlockRendererDispatcher.getBlockModelShapes ()Lnet/minecraft/client/renderer/BlockModelShapes;
    ALOAD 2
    INVOKEVIRTUAL net/minecraft/client/renderer/BlockModelShapes.getTexture (Lnet/minecraft/block/state/IBlockState;)Lnet/minecraft/client/renderer/texture/TextureAtlasSprite;
    INVOKESPECIAL net/minecraft/client/renderer/ItemRenderer.renderBlockInHand (FLnet/minecraft/client/renderer/texture/TextureAtlasSprite;)V
   L2
    LINENUMBER 491 L2
   FRAME FULL [net/minecraft/client/renderer/ItemRenderer F] []
    ALOAD 0
    GETFIELD net/minecraft/client/renderer/ItemRenderer.mc : Lnet/minecraft/client/Minecraft;
    GETFIELD net/minecraft/client/Minecraft.thePlayer : Lnet/minecraft/client/entity/EntityPlayerSP;
    INVOKEVIRTUAL net/minecraft/client/entity/EntityPlayerSP.isSpectator ()Z
    IFNE L20
   L21
    LINENUMBER 493 L21
    ALOAD 0
    GETFIELD net/minecraft/client/renderer/ItemRenderer.mc : Lnet/minecraft/client/Minecraft;
    GETFIELD net/minecraft/client/Minecraft.thePlayer : Lnet/minecraft/client/entity/EntityPlayerSP;
    GETSTATIC net/minecraft/block/material/Material.WATER : Lnet/minecraft/block/material/Material;
    INVOKEVIRTUAL net/minecraft/client/entity/EntityPlayerSP.isInsideOfMaterial (Lnet/minecraft/block/material/Material;)Z
    IFEQ L22
   L23
    LINENUMBER 495 L23
    ALOAD 0
    GETFIELD net/minecraft/client/renderer/ItemRenderer.mc : Lnet/minecraft/client/Minecraft;
    GETFIELD net/minecraft/client/Minecraft.thePlayer : Lnet/minecraft/client/entity/EntityPlayerSP;
    FLOAD 1
    INVOKESTATIC net/minecraftforge/event/ForgeEventFactory.renderWaterOverlay (Lnet/minecraft/entity/player/EntityPlayer;F)Z
    IFNE L22
   L24
    LINENUMBER 496 L24
    ALOAD 0
    FLOAD 1
    INVOKESPECIAL net/minecraft/client/renderer/ItemRenderer.renderWaterOverlayTexture (F)V
   L22
    LINENUMBER 499 L22
   FRAME FULL [net/minecraft/client/renderer/ItemRenderer F] []
    ALOAD 0
    GETFIELD net/minecraft/client/renderer/ItemRenderer.mc : Lnet/minecraft/client/Minecraft;
    GETFIELD net/minecraft/client/Minecraft.thePlayer : Lnet/minecraft/client/entity/EntityPlayerSP;
    INVOKEVIRTUAL net/minecraft/client/entity/EntityPlayerSP.isBurning ()Z
    IFEQ L20
   L25
    LINENUMBER 501 L25
    ALOAD 0
    GETFIELD net/minecraft/client/renderer/ItemRenderer.mc : Lnet/minecraft/client/Minecraft;
    GETFIELD net/minecraft/client/Minecraft.thePlayer : Lnet/minecraft/client/entity/EntityPlayerSP;
    FLOAD 1
    INVOKESTATIC net/minecraftforge/event/ForgeEventFactory.renderFireOverlay (Lnet/minecraft/entity/player/EntityPlayer;F)Z
    IFNE L20
   L26
    LINENUMBER 502 L26
    ALOAD 0
    FLOAD 1
    INVOKESPECIAL net/minecraft/client/renderer/ItemRenderer.renderFireInFirstPerson (F)V
   L20
    LINENUMBER 506 L20
   FRAME FULL [net/minecraft/client/renderer/ItemRenderer F] []
    INVOKESTATIC net/minecraft/client/renderer/GlStateManager.enableAlpha ()V
   L27
    LINENUMBER 507 L27
    RETURN
   L28
    LOCALVARIABLE d0 D L10 L15 6
    LOCALVARIABLE d1 D L11 L15 8
    LOCALVARIABLE d2 D L12 L15 10
    LOCALVARIABLE blockpos Lnet/minecraft/util/math/BlockPos; L13 L15 12
    LOCALVARIABLE iblockstate1 Lnet/minecraft/block/state/IBlockState; L14 L15 13
    LOCALVARIABLE i I L7 L8 5
    LOCALVARIABLE iblockstate Lnet/minecraft/block/state/IBlockState; L4 L2 2
    LOCALVARIABLE overlayPos Lnet/minecraft/util/math/BlockPos; L5 L2 3
    LOCALVARIABLE entityplayer Lnet/minecraft/entity/player/EntityPlayer; L6 L2 4
    LOCALVARIABLE this Lnet/minecraft/client/renderer/ItemRenderer; L0 L28 0
    LOCALVARIABLE partialTicks F L0 L28 1
    MAXSTACK = 8
    MAXLOCALS = 14

  // access flags 0x2
  private renderBlockInHand(FLnet/minecraft/client/renderer/texture/TextureAtlasSprite;)V
   L0
    LINENUMBER 514 L0
    ALOAD 0
    GETFIELD net/minecraft/client/renderer/ItemRenderer.mc : Lnet/minecraft/client/Minecraft;
    INVOKEVIRTUAL net/minecraft/client/Minecraft.getTextureManager ()Lnet/minecraft/client/renderer/texture/TextureManager;
    GETSTATIC net/minecraft/client/renderer/texture/TextureMap.LOCATION_BLOCKS_TEXTURE : Lnet/minecraft/util/ResourceLocation;
    INVOKEVIRTUAL net/minecraft/client/renderer/texture/TextureManager.bindTexture (Lnet/minecraft/util/ResourceLocation;)V
   L1
    LINENUMBER 515 L1
    INVOKESTATIC net/minecraft/client/renderer/Tessellator.getInstance ()Lnet/minecraft/client/renderer/Tessellator;
    ASTORE 3
   L2
    LINENUMBER 516 L2
    ALOAD 3
    INVOKEVIRTUAL net/minecraft/client/renderer/Tessellator.getBuffer ()Lnet/minecraft/client/renderer/VertexBuffer;
    ASTORE 4
   L3
    LINENUMBER 517 L3
    LDC 0.1
    FSTORE 5
   L4
    LINENUMBER 518 L4
    LDC 0.1
    LDC 0.1
    LDC 0.1
    LDC 0.5
    INVOKESTATIC net/minecraft/client/renderer/GlStateManager.color (FFFF)V
   L5
    LINENUMBER 519 L5
    INVOKESTATIC net/minecraft/client/renderer/GlStateManager.pushMatrix ()V
   L6
    LINENUMBER 520 L6
    LDC -1.0
    FSTORE 6
   L7
    LINENUMBER 521 L7
    FCONST_1
    FSTORE 7
   L8
    LINENUMBER 522 L8
    LDC -1.0
    FSTORE 8
   L9
    LINENUMBER 523 L9
    FCONST_1
    FSTORE 9
   L10
    LINENUMBER 524 L10
    LDC -0.5
    FSTORE 10
   L11
    LINENUMBER 525 L11
    ALOAD 2
    INVOKEVIRTUAL net/minecraft/client/renderer/texture/TextureAtlasSprite.getMinU ()F
    FSTORE 11
   L12
    LINENUMBER 526 L12
    ALOAD 2
    INVOKEVIRTUAL net/minecraft/client/renderer/texture/TextureAtlasSprite.getMaxU ()F
    FSTORE 12
   L13
    LINENUMBER 527 L13
    ALOAD 2
    INVOKEVIRTUAL net/minecraft/client/renderer/texture/TextureAtlasSprite.getMinV ()F
    FSTORE 13
   L14
    LINENUMBER 528 L14
    ALOAD 2
    INVOKEVIRTUAL net/minecraft/client/renderer/texture/TextureAtlasSprite.getMaxV ()F
    FSTORE 14
   L15
    LINENUMBER 529 L15
    ALOAD 4
    BIPUSH 7
    GETSTATIC net/minecraft/client/renderer/vertex/DefaultVertexFormats.POSITION_TEX : Lnet/minecraft/client/renderer/vertex/VertexFormat;
    INVOKEVIRTUAL net/minecraft/client/renderer/VertexBuffer.begin (ILnet/minecraft/client/renderer/vertex/VertexFormat;)V
   L16
    LINENUMBER 530 L16
    ALOAD 4
    LDC -1.0
    LDC -1.0
    LDC -0.5
    INVOKEVIRTUAL net/minecraft/client/renderer/VertexBuffer.pos (DDD)Lnet/minecraft/client/renderer/VertexBuffer;
    FLOAD 12
    F2D
    FLOAD 14
    F2D
    INVOKEVIRTUAL net/minecraft/client/renderer/VertexBuffer.tex (DD)Lnet/minecraft/client/renderer/VertexBuffer;
    INVOKEVIRTUAL net/minecraft/client/renderer/VertexBuffer.endVertex ()V
   L17
    LINENUMBER 531 L17
    ALOAD 4
    DCONST_1
    LDC -1.0
    LDC -0.5
    INVOKEVIRTUAL net/minecraft/client/renderer/VertexBuffer.pos (DDD)Lnet/minecraft/client/renderer/VertexBuffer;
    FLOAD 11
    F2D
    FLOAD 14
    F2D
    INVOKEVIRTUAL net/minecraft/client/renderer/VertexBuffer.tex (DD)Lnet/minecraft/client/renderer/VertexBuffer;
    INVOKEVIRTUAL net/minecraft/client/renderer/VertexBuffer.endVertex ()V
   L18
    LINENUMBER 532 L18
    ALOAD 4
    DCONST_1
    DCONST_1
    LDC -0.5
    INVOKEVIRTUAL net/minecraft/client/renderer/VertexBuffer.pos (DDD)Lnet/minecraft/client/renderer/VertexBuffer;
    FLOAD 11
    F2D
    FLOAD 13
    F2D
    INVOKEVIRTUAL net/minecraft/client/renderer/VertexBuffer.tex (DD)Lnet/minecraft/client/renderer/VertexBuffer;
    INVOKEVIRTUAL net/minecraft/client/renderer/VertexBuffer.endVertex ()V
   L19
    LINENUMBER 533 L19
    ALOAD 4
    LDC -1.0
    DCONST_1
    LDC -0.5
    INVOKEVIRTUAL net/minecraft/client/renderer/VertexBuffer.pos (DDD)Lnet/minecraft/client/renderer/VertexBuffer;
    FLOAD 12
    F2D
    FLOAD 13
    F2D
    INVOKEVIRTUAL net/minecraft/client/renderer/VertexBuffer.tex (DD)Lnet/minecraft/client/renderer/VertexBuffer;
    INVOKEVIRTUAL net/minecraft/client/renderer/VertexBuffer.endVertex ()V
   L20
    LINENUMBER 534 L20
    ALOAD 3
    INVOKEVIRTUAL net/minecraft/client/renderer/Tessellator.draw ()V
   L21
    LINENUMBER 535 L21
    INVOKESTATIC net/minecraft/client/renderer/GlStateManager.popMatrix ()V
   L22
    LINENUMBER 536 L22
    FCONST_1
    FCONST_1
    FCONST_1
    FCONST_1
    INVOKESTATIC net/minecraft/client/renderer/GlStateManager.color (FFFF)V
   L23
    LINENUMBER 537 L23
    RETURN
   L24
    LOCALVARIABLE this Lnet/minecraft/client/renderer/ItemRenderer; L0 L24 0
    LOCALVARIABLE partialTicks F L0 L24 1
    LOCALVARIABLE atlas Lnet/minecraft/client/renderer/texture/TextureAtlasSprite; L0 L24 2
    LOCALVARIABLE tessellator Lnet/minecraft/client/renderer/Tessellator; L2 L24 3
    LOCALVARIABLE vertexbuffer Lnet/minecraft/client/renderer/VertexBuffer; L3 L24 4
    LOCALVARIABLE f F L4 L24 5
    LOCALVARIABLE f1 F L7 L24 6
    LOCALVARIABLE f2 F L8 L24 7
    LOCALVARIABLE f3 F L9 L24 8
    LOCALVARIABLE f4 F L10 L24 9
    LOCALVARIABLE f5 F L11 L24 10
    LOCALVARIABLE f6 F L12 L24 11
    LOCALVARIABLE f7 F L13 L24 12
    LOCALVARIABLE f8 F L14 L24 13
    LOCALVARIABLE f9 F L15 L24 14
    MAXSTACK = 7
    MAXLOCALS = 15

  // access flags 0x2
  private renderWaterOverlayTexture(F)V
   L0
    LINENUMBER 545 L0
    ALOAD 0
    GETFIELD net/minecraft/client/renderer/ItemRenderer.mc : Lnet/minecraft/client/Minecraft;
    INVOKEVIRTUAL net/minecraft/client/Minecraft.getTextureManager ()Lnet/minecraft/client/renderer/texture/TextureManager;
    GETSTATIC net/minecraft/client/renderer/ItemRenderer.RES_UNDERWATER_OVERLAY : Lnet/minecraft/util/ResourceLocation;
    INVOKEVIRTUAL net/minecraft/client/renderer/texture/TextureManager.bindTexture (Lnet/minecraft/util/ResourceLocation;)V
   L1
    LINENUMBER 546 L1
    INVOKESTATIC net/minecraft/client/renderer/Tessellator.getInstance ()Lnet/minecraft/client/renderer/Tessellator;
    ASTORE 2
   L2
    LINENUMBER 547 L2
    ALOAD 2
    INVOKEVIRTUAL net/minecraft/client/renderer/Tessellator.getBuffer ()Lnet/minecraft/client/renderer/VertexBuffer;
    ASTORE 3
   L3
    LINENUMBER 548 L3
    ALOAD 0
    GETFIELD net/minecraft/client/renderer/ItemRenderer.mc : Lnet/minecraft/client/Minecraft;
    GETFIELD net/minecraft/client/Minecraft.thePlayer : Lnet/minecraft/client/entity/EntityPlayerSP;
    FLOAD 1
    INVOKEVIRTUAL net/minecraft/client/entity/EntityPlayerSP.getBrightness (F)F
    FSTORE 4
   L4
    LINENUMBER 549 L4
    FLOAD 4
    FLOAD 4
    FLOAD 4
    LDC 0.5
    INVOKESTATIC net/minecraft/client/renderer/GlStateManager.color (FFFF)V
   L5
    LINENUMBER 550 L5
    INVOKESTATIC net/minecraft/client/renderer/GlStateManager.enableBlend ()V
   L6
    LINENUMBER 551 L6
    GETSTATIC net/minecraft/client/renderer/GlStateManager$SourceFactor.SRC_ALPHA : Lnet/minecraft/client/renderer/GlStateManager$SourceFactor;
    GETSTATIC net/minecraft/client/renderer/GlStateManager$DestFactor.ONE_MINUS_SRC_ALPHA : Lnet/minecraft/client/renderer/GlStateManager$DestFactor;
    GETSTATIC net/minecraft/client/renderer/GlStateManager$SourceFactor.ONE : Lnet/minecraft/client/renderer/GlStateManager$SourceFactor;
    GETSTATIC net/minecraft/client/renderer/GlStateManager$DestFactor.ZERO : Lnet/minecraft/client/renderer/GlStateManager$DestFactor;
    INVOKESTATIC net/minecraft/client/renderer/GlStateManager.tryBlendFuncSeparate (Lnet/minecraft/client/renderer/GlStateManager$SourceFactor;Lnet/minecraft/client/renderer/GlStateManager$DestFactor;Lnet/minecraft/client/renderer/GlStateManager$SourceFactor;Lnet/minecraft/client/renderer/GlStateManager$DestFactor;)V
   L7
    LINENUMBER 552 L7
    INVOKESTATIC net/minecraft/client/renderer/GlStateManager.pushMatrix ()V
   L8
    LINENUMBER 553 L8
    LDC 4.0
    FSTORE 5
   L9
    LINENUMBER 554 L9
    LDC -1.0
    FSTORE 6
   L10
    LINENUMBER 555 L10
    FCONST_1
    FSTORE 7
   L11
    LINENUMBER 556 L11
    LDC -1.0
    FSTORE 8
   L12
    LINENUMBER 557 L12
    FCONST_1
    FSTORE 9
   L13
    LINENUMBER 558 L13
    LDC -0.5
    FSTORE 10
   L14
    LINENUMBER 559 L14
    ALOAD 0
    GETFIELD net/minecraft/client/renderer/ItemRenderer.mc : Lnet/minecraft/client/Minecraft;
    GETFIELD net/minecraft/client/Minecraft.thePlayer : Lnet/minecraft/client/entity/EntityPlayerSP;
    GETFIELD net/minecraft/client/entity/EntityPlayerSP.rotationYaw : F
    FNEG
    LDC 64.0
    FDIV
    FSTORE 11
   L15
    LINENUMBER 560 L15
    ALOAD 0
    GETFIELD net/minecraft/client/renderer/ItemRenderer.mc : Lnet/minecraft/client/Minecraft;
    GETFIELD net/minecraft/client/Minecraft.thePlayer : Lnet/minecraft/client/entity/EntityPlayerSP;
    GETFIELD net/minecraft/client/entity/EntityPlayerSP.rotationPitch : F
    LDC 64.0
    FDIV
    FSTORE 12
   L16
    LINENUMBER 561 L16
    ALOAD 3
    BIPUSH 7
    GETSTATIC net/minecraft/client/renderer/vertex/DefaultVertexFormats.POSITION_TEX : Lnet/minecraft/client/renderer/vertex/VertexFormat;
    INVOKEVIRTUAL net/minecraft/client/renderer/VertexBuffer.begin (ILnet/minecraft/client/renderer/vertex/VertexFormat;)V
   L17
    LINENUMBER 562 L17
    ALOAD 3
    LDC -1.0
    LDC -1.0
    LDC -0.5
    INVOKEVIRTUAL net/minecraft/client/renderer/VertexBuffer.pos (DDD)Lnet/minecraft/client/renderer/VertexBuffer;
    LDC 4.0
    FLOAD 11
    FADD
    F2D
    LDC 4.0
    FLOAD 12
    FADD
    F2D
    INVOKEVIRTUAL net/minecraft/client/renderer/VertexBuffer.tex (DD)Lnet/minecraft/client/renderer/VertexBuffer;
    INVOKEVIRTUAL net/minecraft/client/renderer/VertexBuffer.endVertex ()V
   L18
    LINENUMBER 563 L18
    ALOAD 3
    DCONST_1
    LDC -1.0
    LDC -0.5
    INVOKEVIRTUAL net/minecraft/client/renderer/VertexBuffer.pos (DDD)Lnet/minecraft/client/renderer/VertexBuffer;
    FCONST_0
    FLOAD 11
    FADD
    F2D
    LDC 4.0
    FLOAD 12
    FADD
    F2D
    INVOKEVIRTUAL net/minecraft/client/renderer/VertexBuffer.tex (DD)Lnet/minecraft/client/renderer/VertexBuffer;
    INVOKEVIRTUAL net/minecraft/client/renderer/VertexBuffer.endVertex ()V
   L19
    LINENUMBER 564 L19
    ALOAD 3
    DCONST_1
    DCONST_1
    LDC -0.5
    INVOKEVIRTUAL net/minecraft/client/renderer/VertexBuffer.pos (DDD)Lnet/minecraft/client/renderer/VertexBuffer;
    FCONST_0
    FLOAD 11
    FADD
    F2D
    FCONST_0
    FLOAD 12
    FADD
    F2D
    INVOKEVIRTUAL net/minecraft/client/renderer/VertexBuffer.tex (DD)Lnet/minecraft/client/renderer/VertexBuffer;
    INVOKEVIRTUAL net/minecraft/client/renderer/VertexBuffer.endVertex ()V
   L20
    LINENUMBER 565 L20
    ALOAD 3
    LDC -1.0
    DCONST_1
    LDC -0.5
    INVOKEVIRTUAL net/minecraft/client/renderer/VertexBuffer.pos (DDD)Lnet/minecraft/client/renderer/VertexBuffer;
    LDC 4.0
    FLOAD 11
    FADD
    F2D
    FCONST_0
    FLOAD 12
    FADD
    F2D
    INVOKEVIRTUAL net/minecraft/client/renderer/VertexBuffer.tex (DD)Lnet/minecraft/client/renderer/VertexBuffer;
    INVOKEVIRTUAL net/minecraft/client/renderer/VertexBuffer.endVertex ()V
   L21
    LINENUMBER 566 L21
    ALOAD 2
    INVOKEVIRTUAL net/minecraft/client/renderer/Tessellator.draw ()V
   L22
    LINENUMBER 567 L22
    INVOKESTATIC net/minecraft/client/renderer/GlStateManager.popMatrix ()V
   L23
    LINENUMBER 568 L23
    FCONST_1
    FCONST_1
    FCONST_1
    FCONST_1
    INVOKESTATIC net/minecraft/client/renderer/GlStateManager.color (FFFF)V
   L24
    LINENUMBER 569 L24
    INVOKESTATIC net/minecraft/client/renderer/GlStateManager.disableBlend ()V
   L25
    LINENUMBER 570 L25
    RETURN
   L26
    LOCALVARIABLE this Lnet/minecraft/client/renderer/ItemRenderer; L0 L26 0
    LOCALVARIABLE partialTicks F L0 L26 1
    LOCALVARIABLE tessellator Lnet/minecraft/client/renderer/Tessellator; L2 L26 2
    LOCALVARIABLE vertexbuffer Lnet/minecraft/client/renderer/VertexBuffer; L3 L26 3
    LOCALVARIABLE f F L4 L26 4
    LOCALVARIABLE f1 F L9 L26 5
    LOCALVARIABLE f2 F L10 L26 6
    LOCALVARIABLE f3 F L11 L26 7
    LOCALVARIABLE f4 F L12 L26 8
    LOCALVARIABLE f5 F L13 L26 9
    LOCALVARIABLE f6 F L14 L26 10
    LOCALVARIABLE f7 F L15 L26 11
    LOCALVARIABLE f8 F L16 L26 12
    MAXSTACK = 7
    MAXLOCALS = 13

  // access flags 0x2
  private renderFireInFirstPerson(F)V
   L0
    LINENUMBER 577 L0
    INVOKESTATIC net/minecraft/client/renderer/Tessellator.getInstance ()Lnet/minecraft/client/renderer/Tessellator;
    ASTORE 2
   L1
    LINENUMBER 578 L1
    ALOAD 2
    INVOKEVIRTUAL net/minecraft/client/renderer/Tessellator.getBuffer ()Lnet/minecraft/client/renderer/VertexBuffer;
    ASTORE 3
   L2
    LINENUMBER 579 L2
    FCONST_1
    FCONST_1
    FCONST_1
    LDC 0.9
    INVOKESTATIC net/minecraft/client/renderer/GlStateManager.color (FFFF)V
   L3
    LINENUMBER 580 L3
    SIPUSH 519
    INVOKESTATIC net/minecraft/client/renderer/GlStateManager.depthFunc (I)V
   L4
    LINENUMBER 581 L4
    ICONST_0
    INVOKESTATIC net/minecraft/client/renderer/GlStateManager.depthMask (Z)V
   L5
    LINENUMBER 582 L5
    INVOKESTATIC net/minecraft/client/renderer/GlStateManager.enableBlend ()V
   L6
    LINENUMBER 583 L6
    GETSTATIC net/minecraft/client/renderer/GlStateManager$SourceFactor.SRC_ALPHA : Lnet/minecraft/client/renderer/GlStateManager$SourceFactor;
    GETSTATIC net/minecraft/client/renderer/GlStateManager$DestFactor.ONE_MINUS_SRC_ALPHA : Lnet/minecraft/client/renderer/GlStateManager$DestFactor;
    GETSTATIC net/minecraft/client/renderer/GlStateManager$SourceFactor.ONE : Lnet/minecraft/client/renderer/GlStateManager$SourceFactor;
    GETSTATIC net/minecraft/client/renderer/GlStateManager$DestFactor.ZERO : Lnet/minecraft/client/renderer/GlStateManager$DestFactor;
    INVOKESTATIC net/minecraft/client/renderer/GlStateManager.tryBlendFuncSeparate (Lnet/minecraft/client/renderer/GlStateManager$SourceFactor;Lnet/minecraft/client/renderer/GlStateManager$DestFactor;Lnet/minecraft/client/renderer/GlStateManager$SourceFactor;Lnet/minecraft/client/renderer/GlStateManager$DestFactor;)V
   L7
    LINENUMBER 584 L7
    FCONST_1
    FSTORE 4
   L8
    LINENUMBER 586 L8
    ICONST_0
    ISTORE 5
   L9
   FRAME FULL [net/minecraft/client/renderer/ItemRenderer F net/minecraft/client/renderer/Tessellator net/minecraft/client/renderer/VertexBuffer F I] []
    ILOAD 5
    ICONST_2
    IF_ICMPGE L10
   L11
    LINENUMBER 588 L11
    INVOKESTATIC net/minecraft/client/renderer/GlStateManager.pushMatrix ()V
   L12
    LINENUMBER 589 L12
    ALOAD 0
    GETFIELD net/minecraft/client/renderer/ItemRenderer.mc : Lnet/minecraft/client/Minecraft;
    INVOKEVIRTUAL net/minecraft/client/Minecraft.getTextureMapBlocks ()Lnet/minecraft/client/renderer/texture/TextureMap;
    LDC "minecraft:blocks/fire_layer_1"
    INVOKEVIRTUAL net/minecraft/client/renderer/texture/TextureMap.getAtlasSprite (Ljava/lang/String;)Lnet/minecraft/client/renderer/texture/TextureAtlasSprite;
    ASTORE 6
   L13
    LINENUMBER 590 L13
    ALOAD 0
    GETFIELD net/minecraft/client/renderer/ItemRenderer.mc : Lnet/minecraft/client/Minecraft;
    INVOKEVIRTUAL net/minecraft/client/Minecraft.getTextureManager ()Lnet/minecraft/client/renderer/texture/TextureManager;
    GETSTATIC net/minecraft/client/renderer/texture/TextureMap.LOCATION_BLOCKS_TEXTURE : Lnet/minecraft/util/ResourceLocation;
    INVOKEVIRTUAL net/minecraft/client/renderer/texture/TextureManager.bindTexture (Lnet/minecraft/util/ResourceLocation;)V
   L14
    LINENUMBER 591 L14
    ALOAD 6
    INVOKEVIRTUAL net/minecraft/client/renderer/texture/TextureAtlasSprite.getMinU ()F
    FSTORE 7
   L15
    LINENUMBER 592 L15
    ALOAD 6
    INVOKEVIRTUAL net/minecraft/client/renderer/texture/TextureAtlasSprite.getMaxU ()F
    FSTORE 8
   L16
    LINENUMBER 593 L16
    ALOAD 6
    INVOKEVIRTUAL net/minecraft/client/renderer/texture/TextureAtlasSprite.getMinV ()F
    FSTORE 9
   L17
    LINENUMBER 594 L17
    ALOAD 6
    INVOKEVIRTUAL net/minecraft/client/renderer/texture/TextureAtlasSprite.getMaxV ()F
    FSTORE 10
   L18
    LINENUMBER 595 L18
    LDC -0.5
    FSTORE 11
   L19
    LINENUMBER 596 L19
    LDC 0.5
    FSTORE 12
   L20
    LINENUMBER 597 L20
    LDC -0.5
    FSTORE 13
   L21
    LINENUMBER 598 L21
    LDC 0.5
    FSTORE 14
   L22
    LINENUMBER 599 L22
    LDC -0.5
    FSTORE 15
   L23
    LINENUMBER 600 L23
    ILOAD 5
    ICONST_2
    IMUL
    ICONST_1
    ISUB
    INEG
    I2F
    LDC 0.24
    FMUL
    LDC -0.3
    FCONST_0
    INVOKESTATIC net/minecraft/client/renderer/GlStateManager.translate (FFF)V
   L24
    LINENUMBER 601 L24
    ILOAD 5
    ICONST_2
    IMUL
    ICONST_1
    ISUB
    I2F
    LDC 10.0
    FMUL
    FCONST_0
    FCONST_1
    FCONST_0
    INVOKESTATIC net/minecraft/client/renderer/GlStateManager.rotate (FFFF)V
   L25
    LINENUMBER 602 L25
    ALOAD 3
    BIPUSH 7
    GETSTATIC net/minecraft/client/renderer/vertex/DefaultVertexFormats.POSITION_TEX : Lnet/minecraft/client/renderer/vertex/VertexFormat;
    INVOKEVIRTUAL net/minecraft/client/renderer/VertexBuffer.begin (ILnet/minecraft/client/renderer/vertex/VertexFormat;)V
   L26
    LINENUMBER 603 L26
    ALOAD 3
    LDC -0.5
    LDC -0.5
    LDC -0.5
    INVOKEVIRTUAL net/minecraft/client/renderer/VertexBuffer.pos (DDD)Lnet/minecraft/client/renderer/VertexBuffer;
    FLOAD 8
    F2D
    FLOAD 10
    F2D
    INVOKEVIRTUAL net/minecraft/client/renderer/VertexBuffer.tex (DD)Lnet/minecraft/client/renderer/VertexBuffer;
    INVOKEVIRTUAL net/minecraft/client/renderer/VertexBuffer.endVertex ()V
   L27
    LINENUMBER 604 L27
    ALOAD 3
    LDC 0.5
    LDC -0.5
    LDC -0.5
    INVOKEVIRTUAL net/minecraft/client/renderer/VertexBuffer.pos (DDD)Lnet/minecraft/client/renderer/VertexBuffer;
    FLOAD 7
    F2D
    FLOAD 10
    F2D
    INVOKEVIRTUAL net/minecraft/client/renderer/VertexBuffer.tex (DD)Lnet/minecraft/client/renderer/VertexBuffer;
    INVOKEVIRTUAL net/minecraft/client/renderer/VertexBuffer.endVertex ()V
   L28
    LINENUMBER 605 L28
    ALOAD 3
    LDC 0.5
    LDC 0.5
    LDC -0.5
    INVOKEVIRTUAL net/minecraft/client/renderer/VertexBuffer.pos (DDD)Lnet/minecraft/client/renderer/VertexBuffer;
    FLOAD 7
    F2D
    FLOAD 9
    F2D
    INVOKEVIRTUAL net/minecraft/client/renderer/VertexBuffer.tex (DD)Lnet/minecraft/client/renderer/VertexBuffer;
    INVOKEVIRTUAL net/minecraft/client/renderer/VertexBuffer.endVertex ()V
   L29
    LINENUMBER 606 L29
    ALOAD 3
    LDC -0.5
    LDC 0.5
    LDC -0.5
    INVOKEVIRTUAL net/minecraft/client/renderer/VertexBuffer.pos (DDD)Lnet/minecraft/client/renderer/VertexBuffer;
    FLOAD 8
    F2D
    FLOAD 9
    F2D
    INVOKEVIRTUAL net/minecraft/client/renderer/VertexBuffer.tex (DD)Lnet/minecraft/client/renderer/VertexBuffer;
    INVOKEVIRTUAL net/minecraft/client/renderer/VertexBuffer.endVertex ()V
   L30
    LINENUMBER 607 L30
    ALOAD 2
    INVOKEVIRTUAL net/minecraft/client/renderer/Tessellator.draw ()V
   L31
    LINENUMBER 608 L31
    INVOKESTATIC net/minecraft/client/renderer/GlStateManager.popMatrix ()V
   L32
    LINENUMBER 586 L32
    IINC 5 1
    GOTO L9
   L10
    LINENUMBER 611 L10
   FRAME FULL [net/minecraft/client/renderer/ItemRenderer F net/minecraft/client/renderer/Tessellator net/minecraft/client/renderer/VertexBuffer F I] []
    FCONST_1
    FCONST_1
    FCONST_1
    FCONST_1
    INVOKESTATIC net/minecraft/client/renderer/GlStateManager.color (FFFF)V
   L33
    LINENUMBER 612 L33
    INVOKESTATIC net/minecraft/client/renderer/GlStateManager.disableBlend ()V
   L34
    LINENUMBER 613 L34
    ICONST_1
    INVOKESTATIC net/minecraft/client/renderer/GlStateManager.depthMask (Z)V
   L35
    LINENUMBER 614 L35
    SIPUSH 515
    INVOKESTATIC net/minecraft/client/renderer/GlStateManager.depthFunc (I)V
   L36
    LINENUMBER 615 L36
    RETURN
   L37
    LOCALVARIABLE textureatlassprite Lnet/minecraft/client/renderer/texture/TextureAtlasSprite; L13 L32 6
    LOCALVARIABLE f1 F L15 L32 7
    LOCALVARIABLE f2 F L16 L32 8
    LOCALVARIABLE f3 F L17 L32 9
    LOCALVARIABLE f4 F L18 L32 10
    LOCALVARIABLE f5 F L19 L32 11
    LOCALVARIABLE f6 F L20 L32 12
    LOCALVARIABLE f7 F L21 L32 13
    LOCALVARIABLE f8 F L22 L32 14
    LOCALVARIABLE f9 F L23 L32 15
    LOCALVARIABLE i I L9 L10 5
    LOCALVARIABLE this Lnet/minecraft/client/renderer/ItemRenderer; L0 L37 0
    LOCALVARIABLE partialTicks F L0 L37 1
    LOCALVARIABLE tessellator Lnet/minecraft/client/renderer/Tessellator; L1 L37 2
    LOCALVARIABLE vertexbuffer Lnet/minecraft/client/renderer/VertexBuffer; L2 L37 3
    LOCALVARIABLE f F L8 L37 4
    MAXSTACK = 7
    MAXLOCALS = 16

  // access flags 0x1
  public updateEquippedItem()V
   L0
    LINENUMBER 619 L0
    ALOAD 0
    ALOAD 0
    GETFIELD net/minecraft/client/renderer/ItemRenderer.equippedProgressMainHand : F
    PUTFIELD net/minecraft/client/renderer/ItemRenderer.prevEquippedProgressMainHand : F
   L1
    LINENUMBER 620 L1
    ALOAD 0
    ALOAD 0
    GETFIELD net/minecraft/client/renderer/ItemRenderer.equippedProgressOffHand : F
    PUTFIELD net/minecraft/client/renderer/ItemRenderer.prevEquippedProgressOffHand : F
   L2
    LINENUMBER 621 L2
    ALOAD 0
    GETFIELD net/minecraft/client/renderer/ItemRenderer.mc : Lnet/minecraft/client/Minecraft;
    GETFIELD net/minecraft/client/Minecraft.thePlayer : Lnet/minecraft/client/entity/EntityPlayerSP;
    ASTORE 1
   L3
    LINENUMBER 622 L3
    ALOAD 1
    INVOKEVIRTUAL net/minecraft/client/entity/EntityPlayerSP.getHeldItemMainhand ()Lnet/minecraft/item/ItemStack;
    ASTORE 2
   L4
    LINENUMBER 623 L4
    ALOAD 1
    INVOKEVIRTUAL net/minecraft/client/entity/EntityPlayerSP.getHeldItemOffhand ()Lnet/minecraft/item/ItemStack;
    ASTORE 3
   L5
    LINENUMBER 625 L5
    ALOAD 1
    INVOKEVIRTUAL net/minecraft/client/entity/EntityPlayerSP.isRowingBoat ()Z
    IFEQ L6
   L7
    LINENUMBER 627 L7
    ALOAD 0
    ALOAD 0
    GETFIELD net/minecraft/client/renderer/ItemRenderer.equippedProgressMainHand : F
    LDC 0.4
    FSUB
    FCONST_0
    FCONST_1
    INVOKESTATIC net/minecraft/util/math/MathHelper.clamp_float (FFF)F
    PUTFIELD net/minecraft/client/renderer/ItemRenderer.equippedProgressMainHand : F
   L8
    LINENUMBER 628 L8
    ALOAD 0
    ALOAD 0
    GETFIELD net/minecraft/client/renderer/ItemRenderer.equippedProgressOffHand : F
    LDC 0.4
    FSUB
    FCONST_0
    FCONST_1
    INVOKESTATIC net/minecraft/util/math/MathHelper.clamp_float (FFF)F
    PUTFIELD net/minecraft/client/renderer/ItemRenderer.equippedProgressOffHand : F
    GOTO L9
   L6
    LINENUMBER 632 L6
   FRAME FULL [net/minecraft/client/renderer/ItemRenderer net/minecraft/client/entity/EntityPlayerSP net/minecraft/item/ItemStack net/minecraft/item/ItemStack] []
    ALOAD 1
    FCONST_1
    INVOKEVIRTUAL net/minecraft/client/entity/EntityPlayerSP.getCooledAttackStrength (F)F
    FSTORE 4
   L10
    LINENUMBER 633 L10
    ALOAD 0
    DUP
    GETFIELD net/minecraft/client/renderer/ItemRenderer.equippedProgressMainHand : F
    ALOAD 0
    GETFIELD net/minecraft/client/renderer/ItemRenderer.itemStackMainHand : Lnet/minecraft/item/ItemStack;
    ALOAD 2
    ALOAD 1
    GETFIELD net/minecraft/client/entity/EntityPlayerSP.inventory : Lnet/minecraft/entity/player/InventoryPlayer;
    GETFIELD net/minecraft/entity/player/InventoryPlayer.currentItem : I
    INVOKESTATIC net/minecraftforge/client/ForgeHooksClient.shouldCauseReequipAnimation (Lnet/minecraft/item/ItemStack;Lnet/minecraft/item/ItemStack;I)Z
    IFNE L11
    FLOAD 4
    FLOAD 4
    FMUL
    FLOAD 4
    FMUL
    GOTO L12
   L11
   FRAME FULL [net/minecraft/client/renderer/ItemRenderer net/minecraft/client/entity/EntityPlayerSP net/minecraft/item/ItemStack net/minecraft/item/ItemStack F] [net/minecraft/client/renderer/ItemRenderer F]
    FCONST_0
   L12
   FRAME FULL [net/minecraft/client/renderer/ItemRenderer net/minecraft/client/entity/EntityPlayerSP net/minecraft/item/ItemStack net/minecraft/item/ItemStack F] [net/minecraft/client/renderer/ItemRenderer F F]
    ALOAD 0
    GETFIELD net/minecraft/client/renderer/ItemRenderer.equippedProgressMainHand : F
    FSUB
    LDC -0.4
    LDC 0.4
    INVOKESTATIC net/minecraft/util/math/MathHelper.clamp_float (FFF)F
    FADD
    PUTFIELD net/minecraft/client/renderer/ItemRenderer.equippedProgressMainHand : F
   L13
    LINENUMBER 634 L13
    ALOAD 0
    DUP
    GETFIELD net/minecraft/client/renderer/ItemRenderer.equippedProgressOffHand : F
    ALOAD 0
    GETFIELD net/minecraft/client/renderer/ItemRenderer.itemStackOffHand : Lnet/minecraft/item/ItemStack;
    ALOAD 3
    ICONST_M1
    INVOKESTATIC net/minecraftforge/client/ForgeHooksClient.shouldCauseReequipAnimation (Lnet/minecraft/item/ItemStack;Lnet/minecraft/item/ItemStack;I)Z
    IFNE L14
    ICONST_1
    GOTO L15
   L14
   FRAME FULL [net/minecraft/client/renderer/ItemRenderer net/minecraft/client/entity/EntityPlayerSP net/minecraft/item/ItemStack net/minecraft/item/ItemStack F] [net/minecraft/client/renderer/ItemRenderer F]
    ICONST_0
   L15
   FRAME FULL [net/minecraft/client/renderer/ItemRenderer net/minecraft/client/entity/EntityPlayerSP net/minecraft/item/ItemStack net/minecraft/item/ItemStack F] [net/minecraft/client/renderer/ItemRenderer F I]
    I2F
    ALOAD 0
    GETFIELD net/minecraft/client/renderer/ItemRenderer.equippedProgressOffHand : F
    FSUB
    LDC -0.4
    LDC 0.4
    INVOKESTATIC net/minecraft/util/math/MathHelper.clamp_float (FFF)F
    FADD
    PUTFIELD net/minecraft/client/renderer/ItemRenderer.equippedProgressOffHand : F
   L9
    LINENUMBER 637 L9
   FRAME FULL [net/minecraft/client/renderer/ItemRenderer net/minecraft/client/entity/EntityPlayerSP net/minecraft/item/ItemStack net/minecraft/item/ItemStack] []
    ALOAD 0
    GETFIELD net/minecraft/client/renderer/ItemRenderer.equippedProgressMainHand : F
    LDC 0.1
    FCMPG
    IFGE L16
   L17
    LINENUMBER 639 L17
    ALOAD 0
    ALOAD 2
    PUTFIELD net/minecraft/client/renderer/ItemRenderer.itemStackMainHand : Lnet/minecraft/item/ItemStack;
   L16
    LINENUMBER 642 L16
   FRAME FULL [net/minecraft/client/renderer/ItemRenderer net/minecraft/client/entity/EntityPlayerSP net/minecraft/item/ItemStack net/minecraft/item/ItemStack] []
    ALOAD 0
    GETFIELD net/minecraft/client/renderer/ItemRenderer.equippedProgressOffHand : F
    LDC 0.1
    FCMPG
    IFGE L18
   L19
    LINENUMBER 644 L19
    ALOAD 0
    ALOAD 3
    PUTFIELD net/minecraft/client/renderer/ItemRenderer.itemStackOffHand : Lnet/minecraft/item/ItemStack;
   L18
    LINENUMBER 646 L18
   FRAME FULL [net/minecraft/client/renderer/ItemRenderer net/minecraft/client/entity/EntityPlayerSP net/minecraft/item/ItemStack net/minecraft/item/ItemStack] []
    RETURN
   L20
    LOCALVARIABLE f F L10 L9 4
    LOCALVARIABLE this Lnet/minecraft/client/renderer/ItemRenderer; L0 L20 0
    LOCALVARIABLE entityplayersp Lnet/minecraft/client/entity/EntityPlayerSP; L3 L20 1
    LOCALVARIABLE itemstack Lnet/minecraft/item/ItemStack; L4 L20 2
    LOCALVARIABLE itemstack1 Lnet/minecraft/item/ItemStack; L5 L20 3
    MAXSTACK = 5
    MAXLOCALS = 5

  // access flags 0x1
  public resetEquippedProgress(Lnet/minecraft/util/EnumHand;)V
   L0
    LINENUMBER 650 L0
    ALOAD 1
    GETSTATIC net/minecraft/util/EnumHand.MAIN_HAND : Lnet/minecraft/util/EnumHand;
    IF_ACMPNE L1
   L2
    LINENUMBER 652 L2
    ALOAD 0
    FCONST_0
    PUTFIELD net/minecraft/client/renderer/ItemRenderer.equippedProgressMainHand : F
    GOTO L3
   L1
    LINENUMBER 656 L1
   FRAME FULL [net/minecraft/client/renderer/ItemRenderer net/minecraft/util/EnumHand] []
    ALOAD 0
    FCONST_0
    PUTFIELD net/minecraft/client/renderer/ItemRenderer.equippedProgressOffHand : F
   L3
    LINENUMBER 658 L3
   FRAME FULL [net/minecraft/client/renderer/ItemRenderer net/minecraft/util/EnumHand] []
    RETURN
   L4
    LOCALVARIABLE this Lnet/minecraft/client/renderer/ItemRenderer; L0 L4 0
    LOCALVARIABLE hand Lnet/minecraft/util/EnumHand; L0 L4 1
    MAXSTACK = 2
    MAXLOCALS = 2

  // access flags 0x8
  static <clinit>()V
   L0
    LINENUMBER 37 L0
    NEW net/minecraft/util/ResourceLocation
    DUP
    LDC "textures/map/map_background.png"
    INVOKESPECIAL net/minecraft/util/ResourceLocation.<init> (Ljava/lang/String;)V
    PUTSTATIC net/minecraft/client/renderer/ItemRenderer.RES_MAP_BACKGROUND : Lnet/minecraft/util/ResourceLocation;
   L1
    LINENUMBER 38 L1
    NEW net/minecraft/util/ResourceLocation
    DUP
    LDC "textures/misc/underwater.png"
    INVOKESPECIAL net/minecraft/util/ResourceLocation.<init> (Ljava/lang/String;)V
    PUTSTATIC net/minecraft/client/renderer/ItemRenderer.RES_UNDERWATER_OVERLAY : Lnet/minecraft/util/ResourceLocation;
    RETURN
    MAXSTACK = 3
    MAXLOCALS = 0
}
